{
  "product_id": "pimprod2044487",
  "product_url": "https://www.ulta.com/p/travel-size-charlottes-magic-hydration-revival-cleanser-pimprod2044487",
  "extracted_at": "2025-09-23T05:27:59.427963+00:00",
  "product_name": "Charlotte TilburyTravel Size Charlotte's Magic Hydration Revival Cleanser",
  "brand": "Charlotte Tilbury",
  "categories": [
    "Home",
    "Skin Care",
    "Cleansers",
    "Face Wash"
  ],
  "category_keys": [
    "home",
    "skin-care",
    "cleansers",
    "face"
  ],
  "currency": "USD",
  "list_price": "",
  "sale_price": "15.00",
  "availability": "in_stock",
  "rating_avg": "",
  "rating_count": "",
  "images": [
    "https://media.ulta.com/i/ulta/2621969?w=500&h=500"
  ],
  "detailed_images": [
    "https://media.ulta.com/i/ulta/2621969?w=600&h=600&fmt=auto",
    "https://media.ulta.com/i/ulta/2621969_alt01?w=600&h=600&fmt=auto",
    "https://media.ulta.com/i/ulta/2621969_alt02?w=600&h=600&fmt=auto",
    "https://media.ulta.com/i/ulta/2621969_alt03?w=600&h=600&fmt=auto",
    "https://media.ulta.com/i/ulta/2621969_alt04?w=600&h=600&fmt=auto",
    "https://media.ulta.com/i/ulta/2621969_alt05?w=600&h=600&fmt=auto",
    "https://media.ulta.com/i/ulta/2621969_alt06?w=600&h=600&fmt=auto",
    "https://media.ulta.com/i/ulta/2621969_alt07?w=600&h=600&fmt=auto"
  ],
  "summary": "SummaryCharlotte's Magic Hydration Revival Cleanser deeply cleanses, gently removes makeup, and instantly hydrates without stripping or drying.",
  "details": "DetailsBenefits3-in-1 cleanserReduces the look of poresImproves the appearance of tone and texturePlumps skin with hydration that continues post-cleanse, even after rinsingResearch ResultsInstant results: Skin is immediately 2x more hydrated + stays hydrated for up to 24 hours*In just 1 week: Skin feels instantly revived and appears 97% clearer + smoother in 7 days*In just 2 weeks: Skin looks glowing + radiant in 7 days and pores appear reduced by 4x in 14 days**Tested on 33 peopleKey IngredientsHydrating Hyaluronic Acid: Powerful hydration for smoother, plumper looking skinSkin-Smoothing Peptide Complex: Reduces the apperance of pores and refines skin tone appearanceBiomimetic Barrier Shield Technology: Protects and replenishes the skin barrier to prevent water lossItem 2621969How To UseAs a cleanser:Apply a small amount to the palm of the hand.Add a couple of drops of water then gently rub hands together.Apply evenly across the face and massage into skin.Use AM + PM to deeply cleanse, purify and melt away all makeup + impurities.For best results, use Charlotte's Magic Cream or Magic Water Cream after Charlotte's Magic Hydration Revival Cleanser for immediate skin revival and the perfect base for makeup.IngredientsAqua/Water/Eau, Glycerin, Sodium Cocoyl Glycinate, Disodium Cocoyl Glutamate, Citric Acid, Decyl Glucoside, Glyceryl Stearate Se, Sodium Cocoyl Glutamate, Sodium Benzoate, Glycol Distearate, Pentylene Glycol, Cetyl Hydroxyethylcellulose, Hydrolyzed Cottonseed Protein, Fructose, Sodium Hydroxide, Urea, Parfum (Fragrance), Opuntia Ficus-Indica Stem Extract, Tetrasodium Glutamate Diacetate, Allantoin, Maltose, Sodium Chloride, Sodium Lactate, Sodium PCA, Trehalose, Sodium Hyaluronate, Phenoxyethanol, Aloe Barbadensis Leaf Juice Powder, Butyrospermum Parkii (Shea) Butter, Sodium Ascorbyl Phosphate, Tocopheryl Acetate, Camellia Oleifera (Camellia) Seed Oil, Rosa Canina Fruit Oil, Helianthus Annuus (Sunflower) Seed Oil, Disodium EDTA, Potassium Sorbate, Disodium Phosphate, Hydrated Silica, Glucose, Silica Dimethyl Silylate, Sodium Phosphate, Plumeria Rubra Flower Extract, Tocopherol, Hexyl Cinnamal, Benzyl Benzoate.Shipping & Coupon RestrictionsThis brand is excluded from most Ulta Beauty coupons.See brand eligibility details",
  "how_to_use": "As a cleanser:Apply a small amount to the palm of the hand.Add a couple of drops of water then gently rub hands together.Apply evenly across the face and massage into skin.Use AM + PM to deeply cleanse, purify and melt away all makeup + impurities.For best results, use Charlotte's Magic Cream or Magic Water Cream after Charlotte's Magic Hydration Revival Cleanser for immediate skin revival and the perfect base for makeup.",
  "ingredients": [
    "Aqua/Water/Eau",
    "Glycerin",
    "Sodium Cocoyl Glycinate",
    "Disodium Cocoyl Glutamate",
    "Citric Acid",
    "Decyl Glucoside",
    "Glyceryl Stearate Se",
    "Sodium Cocoyl Glutamate",
    "Sodium Benzoate",
    "Glycol Distearate",
    "Pentylene Glycol",
    "Cetyl Hydroxyethylcellulose",
    "Hydrolyzed Cottonseed Protein",
    "Fructose",
    "Sodium Hydroxide",
    "Urea",
    "Parfum (Fragrance)",
    "Opuntia Ficus-Indica Stem Extract",
    "Tetrasodium Glutamate Diacetate",
    "Allantoin",
    "Maltose",
    "Sodium Chloride",
    "Sodium Lactate",
    "Sodium PCA",
    "Trehalose",
    "Sodium Hyaluronate",
    "Phenoxyethanol",
    "Aloe Barbadensis Leaf Juice Powder",
    "Butyrospermum Parkii (Shea) Butter",
    "Sodium Ascorbyl Phosphate",
    "Tocopheryl Acetate",
    "Camellia Oleifera (Camellia) Seed Oil",
    "Rosa Canina Fruit Oil",
    "Helianthus Annuus (Sunflower) Seed Oil",
    "Disodium EDTA",
    "Potassium Sorbate",
    "Disodium Phosphate",
    "Hydrated Silica",
    "Glucose",
    "Silica Dimethyl Silylate",
    "Sodium Phosphate",
    "Plumeria Rubra Flower Extract",
    "Tocopherol",
    "Hexyl Cinnamal",
    "Benzyl Benzoate"
  ],
  "extended_contents": {},
  "tags": {
    "category": [
      "face"
    ],
    "product_type": [
      "cleanser"
    ],
    "skin_type": [
      "dry"
    ],
    "finish": [
      "dewy",
      "long-wear",
      "creamy",
      "powdery",
      "cream",
      "oil"
    ],
    "ingredients": [
      "fragrance"
    ],
    "brand": [
      "mid-range",
      "affordable"
    ],
    "special_features": [
      "hydrating",
      "brightening"
    ]
  },
  "reviews": {
    "product_id": "pimprod2044487",
    "total_reviews": 0,
    "reviews": [],
    "paging": {
      "total_results": 0,
      "pages_total": 0,
      "page_size": 20,
      "current_page_number": 1
    },
    "rollup": {}
  }
}