{
  "product_id": "pimprod2053804",
  "product_url": "https://www.ulta.com/p/awestruck-definition-cream-pimprod2053804",
  "extracted_at": "2025-09-23T03:19:22.070351+00:00",
  "product_name": "CurlsmithAwestruck Definition Cream",
  "brand": "Curlsmith",
  "categories": [
    "Home",
    "Hair",
    "Styling Products",
    "Curl Enhancing"
  ],
  "category_keys": [
    "home",
    "hair",
    "styling-products",
    "curl-enhancing"
  ],
  "currency": "USD",
  "list_price": "",
  "sale_price": "32.00",
  "availability": "in_stock",
  "rating_avg": "",
  "rating_count": "",
  "images": [
    "https://media.ulta.com/i/ulta/2643545?w=500&h=500"
  ],
  "detailed_images": [
    "https://media.ulta.com/i/ulta/2643545?w=600&h=600&fmt=auto",
    "https://media.ulta.com/i/ulta/2643545_alt01?w=600&h=600&fmt=auto",
    "https://media.ulta.com/i/ulta/2643545_alt02?w=600&h=600&fmt=auto",
    "https://media.ulta.com/i/ulta/2643545_alt03?w=600&h=600&fmt=auto",
    "https://media.ulta.com/i/ulta/2643545_alt04?w=600&h=600&fmt=auto",
    "https://media.ulta.com/i/ulta/2643545_alt05?w=600&h=600&fmt=auto",
    "https://media.ulta.com/i/ulta/2643545_alt06?w=600&h=600&fmt=auto",
    "https://media.ulta.com/v/ulta/2643545_vid01/thumbs/8d25230a-4885-462c-9d52-8969d76d96f7?w=600&h=337&fmt=auto"
  ],
  "summary": "SummaryHighlightsCruelty FreeSustainable PackagingGive BackA lightweight styling cream that does it all. It glides on like a dream, delivering just the right amount of hold (level 6!) with a soft, flexible cast. Powered by GEL TRAP technology, the innovative Gel-in-Oil emulsion delivers the deep nourishment of a serum and the definition of a styling gel.",
  "details": "DetailsBenefitsThe formula is expertly balanced to condition without weighing hair down, allowing for natural bounce and movement. With built-in heat and UV protection, it provides 360Â° protection to your curls*, helping defend curls against daily aggressors for healthy-looking curls.5x frizz reduction for up to 3 days*Defines and holds curls for up to 72 hours**Based on third party testing vs controlFeaturesWHO IS IT FOR? All curl types and texturesBEST FOR: Defined, moisturized lasting styleFORMAT: Cream HOLD LEVEL: 6- medium holdSMELLS LIKE: A blend of zesty grapefruit and bright cassis buds with a refreshing twist of mint, wrapped in a playful medley of sun-ripened fruitsColor-SafeMade without sulphates, silicones or drying alcoholsItem 2643545How To UseApply to wet hair and rake through to ensure you are evenly coating all strands. Use the \"praying hands\" method to smooth all locks down. Select your desired styling technique (scrunch/ finger curls/shingle) to enhance and define. Air dry or diffuse.IngredientsWater (Aqua / Eau), Hydrogenated Ethylhexyl Olivate, Propanediol, VP/VA Copolymer, Octyldodecanol, Acrylamidopropyltrimonium Chloride/Acrylates Copolymer, Hydroxypropyl Starch Phosphate, Guar Hydroxypropyltrimonium Chloride, Hydrogenated Olive Oil Unsaponifiables, Helianthus Annuus (Sunflower) Seed Oil, Prunus Armeniaca (Apricot) Kernel Oil, Persea Gratissima (Avocado) Oil, Polyporus Umbellatus (Mushroom) Extract, Selaginella Lepidophylla Extract, Chitosan, Panthenol, Beta-Glucan, Sodium Hyaluronate, Isohexadecane, Helianthus Annuus (Sunflower) Seed Extract, PEG-30 Dipolyhydroxystearate, Octyldodecyl Xyloside, Fructose, Butylene Glycol, Glycerin, Citric Acid, Coceth-7, Ethylhexylglycerin, Tocopherol, Pentylene Glycol, Sorbitan Isostearate, Sodium Citrate, Laurtrimonium Chloride, Sodium Bisulfite, Sodium Benzoate, Potassium Sorbate, Phenoxyethanol, Fragrance (Parfum), Limonene, Citral, Benzaldehyde, Carvone, Citrus Aurantium Peel Oil, Linalyl Acetate.",
  "how_to_use": "Apply to wet hair and rake through to ensure you are evenly coating all strands. Use the \"praying hands\" method to smooth all locks down. Select your desired styling technique (scrunch/ finger curls/shingle) to enhance and define. Air dry or diffuse.",
  "ingredients": [
    "Water (Aqua / Eau)",
    "Hydrogenated Ethylhexyl Olivate",
    "Propanediol",
    "VP/VA Copolymer",
    "Octyldodecanol",
    "Acrylamidopropyltrimonium Chloride/Acrylates Copolymer",
    "Hydroxypropyl Starch Phosphate",
    "Guar Hydroxypropyltrimonium Chloride",
    "Hydrogenated Olive Oil Unsaponifiables",
    "Helianthus Annuus (Sunflower) Seed Oil",
    "Prunus Armeniaca (Apricot) Kernel Oil",
    "Persea Gratissima (Avocado) Oil",
    "Polyporus Umbellatus (Mushroom) Extract",
    "Selaginella Lepidophylla Extract",
    "Chitosan",
    "Panthenol",
    "Beta-Glucan",
    "Sodium Hyaluronate",
    "Isohexadecane",
    "Helianthus Annuus (Sunflower) Seed Extract",
    "PEG-30 Dipolyhydroxystearate",
    "Octyldodecyl Xyloside",
    "Fructose",
    "Butylene Glycol",
    "Glycerin",
    "Citric Acid",
    "Coceth-7",
    "Ethylhexylglycerin",
    "Tocopherol",
    "Pentylene Glycol",
    "Sorbitan Isostearate",
    "Sodium Citrate",
    "Laurtrimonium Chloride",
    "Sodium Bisulfite",
    "Sodium Benzoate",
    "Potassium Sorbate",
    "Phenoxyethanol",
    "Fragrance (Parfum)",
    "Limonene",
    "Citral",
    "Benzaldehyde",
    "Carvone",
    "Citrus Aurantium Peel Oil",
    "Linalyl Acetate"
  ],
  "extended_contents": {},
  "tags": {
    "category": [
      "hair",
      "haircare"
    ],
    "product_type": [
      "moisturizer"
    ],
    "skin_type": [
      "dry",
      "normal"
    ],
    "finish": [
      "sheer",
      "creamy",
      "cream",
      "gel",
      "oil"
    ],
    "ingredients": [
      "fragrance"
    ],
    "brand": [
      "mid-range",
      "mid-range"
    ],
    "special_features": [
      "cruelty-free",
      "natural",
      "spf"
    ]
  },
  "reviews": {
    "product_id": "pimprod2053804",
    "total_reviews": 0,
    "reviews": [],
    "paging": {
      "total_results": 0,
      "pages_total": 0,
      "page_size": 20,
      "current_page_number": 1
    },
    "rollup": {}
  }
}