{
  "product_id": "",
  "product_url": "https://www.ulta.com/p/super-rich-repair-moisturizer-prod2152651",
  "extracted_at": "2025-09-23T05:19:57.076486+00:00",
  "product_name": "DermalogicaSuper Rich Repair Moisturizer",
  "brand": "Dermalogica",
  "categories": [
    "Home",
    "Skin Care",
    "Moisturizers",
    "Face Moisturizer"
  ],
  "category_keys": [
    "home",
    "skin-care",
    "moisturizers",
    "face"
  ],
  "currency": "USD",
  "list_price": "",
  "sale_price": "98.00",
  "availability": "in_stock",
  "rating_avg": "4.8",
  "rating_count": "1266",
  "images": [
    "https://media.ulta.com/i/ulta/2152651?w=500&h=500"
  ],
  "detailed_images": [
    "https://media.ulta.com/i/ulta/2152651?w=600&h=600&fmt=auto",
    "https://media.ulta.com/i/ulta/2152651cm_alt01?w=600&h=600&fmt=auto",
    "https://media.ulta.com/i/ulta/2152651cm_alt02?w=600&h=600&fmt=auto",
    "https://media.ulta.com/i/ulta/2152651cm_alt03?w=600&h=600&fmt=auto",
    "https://media.ulta.com/i/ulta/2152651cm_alt04?w=600&h=600&fmt=auto",
    "https://media.ulta.com/i/ulta/2152651cm_alt05?w=600&h=600&fmt=auto",
    "https://media.ulta.com/i/ulta/2152651cm_alt06?w=600&h=600&fmt=auto",
    "https://media.ulta.com/i/ulta/2152651cm_alt07?w=600&h=600&fmt=auto",
    "https://media.ulta.com/v/ulta/2152651cm_vid01/thumbs/b7c75ce4-8f7c-4869-b076-f60e1a6e93ec?w=600&h=337&fmt=auto"
  ],
  "summary": "SummaryHighlightsClean IngredientsCruelty FreeVeganSustainable PackagingGive BackDermalogica's Super Rich Repair Moisturizer is a deeply nourishing skin treatment that combats chronically dry, dehydrated skin.",
  "details": "DetailsBenefitsThis concentrated, ultra-thick cream is formulated with vegan peptides that stimulate collagen production while an acid-free renewal complex smooths fine lines for dramatically improved elasticity and toneKey IngredientsAllantoin: provides anti-inflammatory and anti-aging benefitsShea Butter: rich in Vitamins and fatty acids to hydrate and softenJojoba Oil: moisturizes without clogging poresFormulated WithoutParabensSulfatesPhthalatesSynthetic FragranceItem 2152651How To UseApply to face and neck with light, upward strokes. Wait for cream to absorb before applying additional products. Use once or twice daily.IngredientsWater/Aqua/Eau, Isohexadecane, Dipropylene Glycol, Caprylic/Capric/Myristic/Stearic Triglyceride, Lauryl PEG-9 Polydimethylsiloxyethyl Dimethicone, Simmondsia Chinensis (Jojoba) Seed Oil, Butyrospermum Parkii (Shea Butter), Dimethicone, Glycerin, Octyldodecyl Neopentanoate, Sodium Chloride, Isostearic Acid, Arginine/Lysine Polypeptide, Palmitoyl Tripeptide-5, Avena Sativa (Oat) Kernel Extract, Pyrus Malus (Apple) Seed Extract, Borago Officinalis Seed Oil, Oenothera Biennis (Evening Primrose) Oil, Hydrogenated Coconut Oil, Gardenia Tahitensis Flotheyr, Algae Extract, Yeast Extract, Glucosamine HC, Tocopheryl Acetate, Sodium Hyaluronate, Colloidal Oatmeal, Madecassoside, Urea, Hexyldecanol, Polyglyceryl-4 Isostearate, Cetyl Dimethicone, Hydrogenated Castor Oil, Butylene Glycol, Phenoxyethanol, Caprylyl Glycol, Ethylhexylglycerin, Hexylene Glycol, Linalool, Citronellol, Geraniol, Cedrus Atlantica Bark Oil, Cupressus Sempervirens Leaf/Stem Extract, Eucalyptus Globulus Leaf Oil, Helianthus Annuus (Sunflotheyr) Seed Oil, Pelargonium Graveolens Flotheyr Oil, Aniba Rosaeodora (Rosewood) Wood Oil, Abies Sibirica Oil, Santalum Album (Sandalwood) Oil.Shipping & Coupon RestrictionsThis brand is excluded from most Ulta Beauty coupons.See brand eligibility details",
  "how_to_use": "Apply to face and neck with light, upward strokes. Wait for cream to absorb before applying additional products. Use once or twice daily.",
  "ingredients": [
    "Water/Aqua/Eau",
    "Isohexadecane",
    "Dipropylene Glycol",
    "Caprylic/Capric/Myristic/Stearic Triglyceride",
    "Lauryl PEG-9 Polydimethylsiloxyethyl Dimethicone",
    "Simmondsia Chinensis (Jojoba) Seed Oil",
    "Butyrospermum Parkii (Shea Butter)",
    "Dimethicone",
    "Glycerin",
    "Octyldodecyl Neopentanoate",
    "Sodium Chloride",
    "Isostearic Acid",
    "Arginine/Lysine Polypeptide",
    "Palmitoyl Tripeptide-5",
    "Avena Sativa (Oat) Kernel Extract",
    "Pyrus Malus (Apple) Seed Extract",
    "Borago Officinalis Seed Oil",
    "Oenothera Biennis (Evening Primrose) Oil",
    "Hydrogenated Coconut Oil",
    "Gardenia Tahitensis Flotheyr",
    "Algae Extract",
    "Yeast Extract",
    "Glucosamine HC",
    "Tocopheryl Acetate",
    "Sodium Hyaluronate",
    "Colloidal Oatmeal",
    "Madecassoside",
    "Urea",
    "Hexyldecanol",
    "Polyglyceryl-4 Isostearate",
    "Cetyl Dimethicone",
    "Hydrogenated Castor Oil",
    "Butylene Glycol",
    "Phenoxyethanol",
    "Caprylyl Glycol",
    "Ethylhexylglycerin",
    "Hexylene Glycol",
    "Linalool",
    "Citronellol",
    "Geraniol",
    "Cedrus Atlantica Bark Oil",
    "Cupressus Sempervirens Leaf/Stem Extract",
    "Eucalyptus Globulus Leaf Oil",
    "Helianthus Annuus (Sunflotheyr) Seed Oil",
    "Pelargonium Graveolens Flotheyr Oil",
    "Aniba Rosaeodora (Rosewood) Wood Oil",
    "Abies Sibirica Oil",
    "Santalum Album (Sandalwood) Oil"
  ],
  "extended_contents": {
    "text": "Show less"
  },
  "tags": {
    "category": [
      "face"
    ],
    "product_type": [
      "moisturizer"
    ],
    "skin_type": [
      "dry",
      "mature"
    ],
    "finish": [
      "sheer",
      "creamy",
      "cream",
      "oil"
    ],
    "ingredients": [
      "peptides"
    ],
    "brand": [
      "mid-range",
      "premium"
    ],
    "special_features": [
      "cruelty-free",
      "vegan",
      "anti-aging",
      "hydrating"
    ]
  },
  "reviews": {
    "product_id": "pimprodsuper-rich-repair-moisturizer-prod2152651",
    "total_reviews": 0,
    "reviews": [],
    "paging": {
      "total_results": 0,
      "pages_total": 0,
      "page_size": 20,
      "current_page_number": 1
    },
    "rollup": {}
  }
}