{
  "product_id": "pimprod2054152",
  "product_url": "https://www.ulta.com/p/rouge-dior-on-stage-pimprod2054152",
  "extracted_at": "2025-09-23T05:05:59.759090+00:00",
  "product_name": "DiorRouge Dior On Stage",
  "brand": "Dior",
  "categories": [
    "Home",
    "Makeup",
    "Lips",
    "Lipstick"
  ],
  "category_keys": [
    "home",
    "makeup",
    "lips",
    "lips"
  ],
  "currency": "USD",
  "list_price": "",
  "sale_price": "48.00",
  "availability": "in_stock",
  "rating_avg": "",
  "rating_count": "",
  "images": [
    "https://media.ulta.com/i/ulta/2645210?w=500&h=500"
  ],
  "detailed_images": [
    "https://media.ulta.com/i/ulta/2645210?w=600&h=600&fmt=auto",
    "https://media.ulta.com/i/ulta/2645210_sm?w=600&h=600&fmt=auto",
    "https://media.ulta.com/i/ulta/2645210_alt01?w=600&h=600&fmt=auto",
    "https://media.ulta.com/i/ulta/2645210cm_alt01?w=600&h=600&fmt=auto",
    "https://media.ulta.com/i/ulta/2645210cm_alt02?w=600&h=600&fmt=auto",
    "https://media.ulta.com/i/ulta/2645210cm_alt03?w=600&h=600&fmt=auto",
    "https://media.ulta.com/i/ulta/2645210cm_alt04?w=600&h=600&fmt=auto",
    "https://media.ulta.com/i/ulta/2645210cm_alt05?w=600&h=600&fmt=auto",
    "https://media.ulta.com/i/ulta/2645210cm_alt06?w=600&h=600&fmt=auto",
    "https://media.ulta.com/v/ulta/2645210cm_vid01/thumbs/377452d8-4527-41d1-b0dd-4426719e561a?w=600&h=337&fmt=auto"
  ],
  "summary": "SummaryRouge Dior On Stage is an ultra longwear lipstick with a shine finish that shapes and hydrates lips, leaving them visibly plump and smooth.",
  "details": "DetailsBenefitsThe lipstick's ultra longwear shine finish combines an \"ultra colour\" phase - which fixes pigments and the color on the lips - and a \"coated shine\" phase - a combination of oils that ensures comfort, suppleness and shine. Lips stay hydrated over time and the color remains the same.FeaturesRouge Dior On Stage's innovative \"double phase\" technology sets pigments and color on the lips, while also ensuring comfort, suppleness and shine. The imperceptible texture visibly smooths lips and the intense color shades remain true over time.Item 2645210How To UseThe bullet has been designed to combine the precision of a lip liner and the fullness of a lipstick. It follows the lips perfectly for ultra-precise application in just one swipe.The rounded shape at the top helps you draw the Cupid's bow on the upper lip.The pointed bottom helps define the lower lip.For optimal application and to preserve the formula, do not wind the bullet more than 2 mm and be sure to close the lid after each use.IngredientsTrimethylsiloxyphenyl Dimethicone, Polyglyceryl-2 Isostearate/Dimer Dilinoleate Copolymer, C9-12 Alkane, Glyceryl Hydrogenated Rosinate, Methyl Hydrogenated Rosinate, Dextrin Isostearate, Isododecane, Sucrose Acetate Isobutyrate, Synthetic Wax, Cellulose, Bis-Hydroxypropyl Dimethicone/Smdi Copolymer, Octyldodecanol, Candelilla Cera (Euphorbia Cerifera (Candelilla) Wax), Polyethylene, Parfum (Fragrance), Lecithin, Simmondsia Chinensis (Jojoba) Seed Oil, Prunus Amygdalus Dulcis (Sweet Almond) Oil, Aluminum Hydroxide, Sodium Myristoyl Glutamate, Punica Granatum Flower Extract, Ethyl Vanillin, Pentaerythrityl Tetra-Di-T-Butyl Hydroxyhydrocinnamate, Synthetic Fluorphlogopite, Polyglyceryl-3 Diisostearate, Ammonium Glycyrrhizate, Disteardimonium Hectorite, Vanillin, Propylene Carbonate, Caprylic/Capric Triglyceride, Polyhydroxystearic Acid, Linalyl Acetate, Terpineol, Isostearic Acid, Tin Oxide, Paeonia Officinalis Flower Extract, Polyglyceryl-3 Polyricinoleate, [+/- CI 77891 (Titanium Dioxide), CI 77491, CI 77492, CI 77499 (Iron Oxides), CI 15850 (Red 7 Lake)].Shipping & Coupon RestrictionsThis brand is excluded from most Ulta Beauty coupons.See brand eligibility details",
  "how_to_use": "The bullet has been designed to combine the precision of a lip liner and the fullness of a lipstick. It follows the lips perfectly for ultra-precise application in just one swipe.The rounded shape at the top helps you draw the Cupid's bow on the upper lip.The pointed bottom helps define the lower lip.For optimal application and to preserve the formula, do not wind the bullet more than 2 mm and be sure to close the lid after each use.",
  "ingredients": [
    "Trimethylsiloxyphenyl Dimethicone",
    "Polyglyceryl-2 Isostearate/Dimer Dilinoleate Copolymer",
    "C9-12 Alkane",
    "Glyceryl Hydrogenated Rosinate",
    "Methyl Hydrogenated Rosinate",
    "Dextrin Isostearate",
    "Isododecane",
    "Sucrose Acetate Isobutyrate",
    "Synthetic Wax",
    "Cellulose",
    "Bis-Hydroxypropyl Dimethicone/Smdi Copolymer",
    "Octyldodecanol",
    "Candelilla Cera (Euphorbia Cerifera (Candelilla) Wax)",
    "Polyethylene",
    "Parfum (Fragrance)",
    "Lecithin",
    "Simmondsia Chinensis (Jojoba) Seed Oil",
    "Prunus Amygdalus Dulcis (Sweet Almond) Oil",
    "Aluminum Hydroxide",
    "Sodium Myristoyl Glutamate",
    "Punica Granatum Flower Extract",
    "Ethyl Vanillin",
    "Pentaerythrityl Tetra-Di-T-Butyl Hydroxyhydrocinnamate",
    "Synthetic Fluorphlogopite",
    "Polyglyceryl-3 Diisostearate",
    "Ammonium Glycyrrhizate",
    "Disteardimonium Hectorite",
    "Vanillin",
    "Propylene Carbonate",
    "Caprylic/Capric Triglyceride",
    "Polyhydroxystearic Acid",
    "Linalyl Acetate",
    "Terpineol",
    "Isostearic Acid",
    "Tin Oxide",
    "Paeonia Officinalis Flower Extract",
    "Polyglyceryl-3 Polyricinoleate",
    "[+/-"
  ],
  "extended_contents": {
    "images": [
      "https://content.syndigo.com/asset/fea8e09d-a18f-4f74-bd4d-fce159e3d7b4/240.jpg",
      "https://content.syndigo.com/asset/f322a7d2-1f90-4684-834e-4f920f0da74a/1920.webp",
      "https://content.syndigo.com/asset/f322a7d2-1f90-4684-834e-4f920f0da74a/240.webp"
    ]
  },
  "tags": {
    "category": [
      "makeup",
      "lips",
      "lip",
      "cosmetics"
    ],
    "product_type": [
      "lipstick"
    ],
    "skin_type": [
      "combination"
    ],
    "finish": [
      "creamy",
      "oil"
    ],
    "ingredients": [
      "synthetic",
      "fragrance"
    ],
    "brand": [
      "luxury",
      "mid-range"
    ],
    "special_features": []
  },
  "reviews": {
    "product_id": "pimprod2054152",
    "total_reviews": 0,
    "reviews": [],
    "paging": {
      "total_results": 0,
      "pages_total": 0,
      "page_size": 20,
      "current_page_number": 1
    },
    "rollup": {}
  }
}