{
  "product_id": "pimprod2053394",
  "product_url": "https://www.ulta.com/p/jelly-pop-vault-pimprod2053394",
  "extracted_at": "2025-09-23T04:18:19.332825+00:00",
  "product_name": "e.l.f. CosmeticsJelly Pop Vault",
  "brand": "e.l.f. Cosmetics",
  "categories": [
    "Home",
    "Makeup",
    "Face",
    "Face Primer"
  ],
  "category_keys": [
    "home",
    "makeup",
    "face",
    "face"
  ],
  "currency": "USD",
  "list_price": "",
  "sale_price": "40.00",
  "availability": "in_stock",
  "rating_avg": "5",
  "rating_count": "1",
  "images": [
    "https://media.ulta.com/i/ulta/2644987?w=500&h=500"
  ],
  "detailed_images": [
    "https://media.ulta.com/i/ulta/2644987?w=600&h=600&fmt=auto",
    "https://media.ulta.com/i/ulta/2644987_alt01?w=600&h=600&fmt=auto",
    "https://media.ulta.com/i/ulta/2644987_alt02?w=600&h=600&fmt=auto",
    "https://media.ulta.com/i/ulta/2644987_alt03?w=600&h=600&fmt=auto",
    "https://media.ulta.com/i/ulta/2644987_alt04?w=600&h=600&fmt=auto",
    "https://media.ulta.com/i/ulta/2644987_alt05?w=600&h=600&fmt=auto",
    "https://media.ulta.com/i/ulta/2644987_alt06?w=600&h=600&fmt=auto"
  ],
  "summary": "SummaryHighlightsCruelty Freee.l.f.'s Jelly Pop Vault features a Dew Primer, Glow Reviver Lip Oil, Makeup Melting Cleansing Balm and Luscious Lip Mask, all in an exclusive pink makeup bag. The delicious formulas grip makeup with a dewy finish, reveal a clean and hydrated complexion, and make lips look nourished and glossy.",
  "details": "DetailsIncludesJelly Pop Dew Primer (1.01 oz)Jelly Pop Glow Reviver Lip Oil (0.25 oz)Jelly Pop Makeup Melting Cleansing Balm (2.0 oz)Jelly Pop Luscious Lip Mask (0.15 oz)Jelly Pop One in a Melon Makeup BagBenefits4-piece makeup and skincare set, featuring full-size products from e.l.f.’s limited-edition Jelly Pop collectionComes in a hot pink Jelly Pop makeup bag that’s exclusive to this vault and UltaHelps cleanse and nourish skin, leaving it with a dewy glowHelps nourish lips and adds glossy color and shineGet your slice for a juicy price: just $40!100% vegan, e.l.f. is double-certified cruelty-free by Leaping Bunny & PETAe.l.f. is proud to partner with Fair Trade USA™ and manufacture products in Fair Trade Certified™ facilities. Look for the Fair Trade Certified™ seal on your e.l.f. product!Formulated WithoutPhthalates, Parabens, Nonylphenol Ethoxylates, Triclosan, TriclocarbanItem 2644987How To UseHow to use Jelly Pop Dew Primer:Apply makeup primer evenly to face prior to makeup application.Once applied, wait 30 seconds before applying makeup.How to use Jelly Pop Glow Reviver Lip Oil:Wear lip oil lone or as a top coat for a juicy splash of shimmer.How to use Jelly Pop Makeup Melting Cleansing Balm:Scoop out a small amount of cleansing balm with the included spatula and massage onto dry skin, ensuring eyes are closed.Rinse with water or remove with a warm, damp cloth.How to use Jelly Pop Luscious Lip Mask:Use the applicator to apply a generous, even layer of lip mask onto clean, dry lips.Reapply as needed throughout the day or leave on overnight.IngredientsJelly Pop Dew Primer: Water (Aqua), Butylene Glycol, Glycerin, PEG-150 Distearate, Polysorbate 80, Phenoxyethanol, PEG-240/Hdicopolymer Bis-Decyltetradeceth-20 Ether, Niacinamide, Pentylene Glycol, Ethylhexylglycerin, Fragrance (Parfum), Caprylyl Glycol, Disodium EDTA, Sodium Hyaluronate, Sodium Ascorbyl Phosphate, Potassium Laurate, Tocopherol, Citrullus Lanatus (Watermelon) Fruit Extract, Limonene, Hydroxycitronellal, Linalool. May Contain: Red 40 (CI 16035).Jelly Pop Glow Reviver Lip Oil: Hydrogenated Polyisobutene, Tridecyl Trimellitate, Hydrogenated Styrene/Isoprene Copolymer, Phytosteryl/Octyldodecyl Lauroyl Glutamate, Polyisobutene, Dextrin Palmitate, Calcium Aluminum Borosilicate, Squalane, Fragrance (Parfum), Tocopheryl Acetate, Diethylhexyl Syringylidenemalonate, Phenoxyethanol, Caprylyl Glycol, Prunus Armeniaca (Apricot) Kernel Oil, Persea Gratissima (Avocado) Oil, Simmondsia Chinensis (Jojoba) Seed Oil, Punica Granatum Seed Oil, Caprylic/Capric Triglyceride, Diisostearyl Malate, Simethicone, Tin Oxide, Water (Aqua), Tocopherol, Butylene Glycol, Citrullus Lanatus (Watermelon) Fruit Extract, Hexyl Cinnamal, Linalool, Limonene. May Contain: Titanium Dioxide (CI 77891), Red 40 Lake (CI 16035), Red 7 Lake (CI 15850), Red 6 Lake (CI 15850), Iron Oxides (CI 77491), Iron Oxides (CI 77492).Jelly Pop Makeup Melting Cleansing Balm: Cetyl Ethylhexanoate, Triethylhexanoin, Hydrogenated Polydecene, PEG-20 Glyceryl Triisostearate, Synthetic Wax, PEG-10 Isostearate, Water (Aqua), Fragrance (Parfum), Phenoxyethanol, Caprylyl Glycol, Ethylhexylglycerin, Butylene Glycol, Hydrolyzed Sodium Hyaluronate, Glycerin, Sodium Lauroyl Lactylate, Carbomer, Citrullus Lanatus (Watermelon) Fruit Extract, Ceramide NP, Ceramide AP, Phytosphingosine, Polysorbate 20, Cholesterol, Xanthan Gum, Palmitoyl Tripeptide-1, Palmitoyl Tetrapeptide-7, Ceramide EOP, Hexyl Cinnamal, Linalool.Jelly Pop Luscious Lip Mask: Triisostearin, Hydrogenated Polyisobutene, Polyglyceryl-10 Pentaisostearate, Dextrin Palmitate, Diethylhexyl Syringylidenemalonate, Ethylhexylglycerin, Fragrance (Parfum), Squalane, Caprylic/Capric Triglyceride, Simethicone, Water (Aqua), Ricinus Communis (Castor) Seed Oil, Glycerin, Tocopherol, Sodium Hyaluronate, Butylene Glycol, Maltodextrin, Hydrogenated Castor Oil, 1,2-Hexanediol, Calcium Pantothenate, Xanthan Gum, Caprylyl Glycol, Urea, Magnesium Lactate, Papain, Phenoxyethanol, Soluble Collagen, Potassium Lactate, Citrullus Lanatus (Watermelon) Fruit Extract, Magnesium Chloride, Proline, Alanine, Serine, Sodium Citrate, Hexyl Cinnamal, Linalool. May Contain: Red 6 Lake (CI 15850), Red 7 Lake (CI 15850).Ingredients may change or vary from time to time. Please refer to the packaging of the product you receive for the list of ingredients in your particular product.",
  "how_to_use": "How to use Jelly Pop Dew Primer:Apply makeup primer evenly to face prior to makeup application.Once applied, wait 30 seconds before applying makeup.How to use Jelly Pop Glow Reviver Lip Oil:Wear lip oil lone or as a top coat for a juicy splash of shimmer.How to use Jelly Pop Makeup Melting Cleansing Balm:Scoop out a small amount of cleansing balm with the included spatula and massage onto dry skin, ensuring eyes are closed.Rinse with water or remove with a warm, damp cloth.How to use Jelly Pop Luscious Lip Mask:Use the applicator to apply a generous, even layer of lip mask onto clean, dry lips.Reapply as needed throughout the day or leave on overnight.",
  "ingredients": [
    "Jelly Pop Dew Primer: Water (Aqua)",
    "Butylene Glycol",
    "Glycerin",
    "PEG-150 Distearate",
    "Polysorbate 80",
    "Phenoxyethanol",
    "PEG-240/Hdicopolymer Bis-Decyltetradeceth-20 Ether",
    "Niacinamide",
    "Pentylene Glycol",
    "Ethylhexylglycerin",
    "Fragrance (Parfum)",
    "Caprylyl Glycol",
    "Disodium EDTA",
    "Sodium Hyaluronate",
    "Sodium Ascorbyl Phosphate",
    "Potassium Laurate",
    "Tocopherol",
    "Citrullus Lanatus (Watermelon) Fruit Extract",
    "Limonene",
    "Hydroxycitronellal",
    "Linalool. May Contain: Red 40 (",
    "Tridecyl Trimellitate",
    "Hydrogenated Styrene/Isoprene Copolymer",
    "Phytosteryl/Octyldodecyl Lauroyl Glutamate",
    "Polyisobutene",
    "Dextrin Palmitate",
    "Calcium Aluminum Borosilicate",
    "Squalane",
    "Fragrance (Parfum)",
    "Tocopheryl Acetate",
    "Diethylhexyl Syringylidenemalonate",
    "Phenoxyethanol",
    "Caprylyl Glycol",
    "Prunus Armeniaca (Apricot) Kernel Oil",
    "Persea Gratissima (Avocado) Oil",
    "Simmondsia Chinensis (Jojoba) Seed Oil",
    "Punica Granatum Seed Oil",
    "Caprylic/Capric Triglyceride",
    "Diisostearyl Malate",
    "Simethicone",
    "Tin Oxide",
    "Water (Aqua)",
    "Tocopherol",
    "Butylene Glycol",
    "Citrullus Lanatus (Watermelon) Fruit Extract",
    "Hexyl Cinnamal",
    "Linalool",
    "Limonene. May Contain: Titanium Dioxide (",
    "Red 40 Lake (",
    "Red 7 Lake (",
    "Red 6 Lake (",
    "Iron Oxides (",
    "Iron Oxides (",
    "Triethylhexanoin",
    "Hydrogenated Polydecene",
    "PEG-20 Glyceryl Triisostearate",
    "Synthetic Wax",
    "PEG-10 Isostearate",
    "Water (Aqua)",
    "Fragrance (Parfum)",
    "Phenoxyethanol",
    "Caprylyl Glycol",
    "Ethylhexylglycerin",
    "Butylene Glycol",
    "Hydrolyzed Sodium Hyaluronate",
    "Glycerin",
    "Sodium Lauroyl Lactylate",
    "Carbomer",
    "Citrullus Lanatus (Watermelon) Fruit Extract",
    "Ceramide NP",
    "Ceramide AP",
    "Phytosphingosine",
    "Polysorbate 20",
    "Cholesterol",
    "Xanthan Gum",
    "Palmitoyl Tripeptide-1",
    "Palmitoyl Tetrapeptide-7",
    "Ceramide EOP",
    "Hexyl Cinnamal",
    "Linalool.Jelly Pop Luscious Lip Mask: Triisostearin",
    "Hydrogenated Polyisobutene",
    "Polyglyceryl-10 Pentaisostearate",
    "Dextrin Palmitate",
    "Diethylhexyl Syringylidenemalonate",
    "Ethylhexylglycerin",
    "Fragrance (Parfum)",
    "Squalane",
    "Caprylic/Capric Triglyceride",
    "Simethicone",
    "Water (Aqua)",
    "Ricinus Communis (Castor) Seed Oil",
    "Glycerin",
    "Tocopherol",
    "Sodium Hyaluronate",
    "Butylene Glycol",
    "Maltodextrin",
    "Hydrogenated Castor Oil",
    "2-Hexanediol",
    "Calcium Pantothenate",
    "Xanthan Gum",
    "Caprylyl Glycol",
    "Urea",
    "Magnesium Lactate",
    "Papain",
    "Phenoxyethanol",
    "Soluble Collagen",
    "Potassium Lactate",
    "Citrullus Lanatus (Watermelon) Fruit Extract",
    "Magnesium Chloride",
    "Proline",
    "Alanine",
    "Serine",
    "Sodium Citrate",
    "Hexyl Cinnamal",
    "Linalool. May Contain: Red 6 Lake (",
    "Red 7 Lake ("
  ],
  "extended_contents": {},
  "tags": {
    "category": [
      "makeup",
      "face",
      "cosmetics"
    ],
    "product_type": [
      "primer"
    ],
    "skin_type": [
      "dry"
    ],
    "finish": [
      "dewy",
      "glossy",
      "sheer",
      "gel",
      "oil"
    ],
    "ingredients": [
      "niacinamide",
      "peptides",
      "ceramides",
      "collagen",
      "synthetic",
      "fragrance"
    ],
    "brand": [
      "mid-range",
      "mid-range"
    ],
    "special_features": [
      "cruelty-free",
      "vegan",
      "purifying"
    ]
  },
  "reviews": {
    "product_id": "pimprod2053394",
    "total_reviews": 1,
    "reviews": [
      {
        "review_id": 558158117,
        "rating": 5,
        "headline": "Cute",
        "comments": "Love the bag and the colors",
        "nickname": "Jan",
        "location": "Utah",
        "created_date": 1753404595657,
        "bottom_line": null,
        "helpful_votes": 7,
        "not_helpful_votes": 2
      }
    ],
    "paging": {
      "total_results": 1,
      "pages_total": 1,
      "page_size": 20,
      "current_page_number": 1
    },
    "rollup": {
      "properties": [],
      "rating_histogram": [
        0,
        0,
        0,
        0,
        1
      ],
      "review_histogram": [
        0,
        0,
        0,
        0,
        1
      ],
      "rating_count": 1,
      "review_count": 1,
      "average_rating": 5.0,
      "recommended_ratio": 0.0,
      "media": [],
      "name": "Jelly Pop Vault",
      "native_review_count": 1,
      "native_sampling_review_count": 0,
      "native_sweepstakes_review_count": 0,
      "native_community_content_review_count": 0,
      "syndicated_review_count": 0,
      "locale": "en_US"
    }
  }
}