{
  "product_id": "pimprod2052476",
  "product_url": "https://www.ulta.com/p/breakout-set-pimprod2052476",
  "extracted_at": "2025-09-23T03:26:20.292284+00:00",
  "product_name": "INKEYThe Breakout Set",
  "brand": "INKEY",
  "categories": [
    "Home",
    "Skin Care",
    "Treatment & Serums",
    "Acne & Blemish Treatments"
  ],
  "category_keys": [
    "home",
    "skin-care",
    "men",
    "men"
  ],
  "currency": "USD",
  "list_price": "",
  "sale_price": "25.50",
  "availability": "in_stock",
  "rating_avg": "4.5",
  "rating_count": "2",
  "images": [
    "https://media.ulta.com/i/ulta/2643909?w=500&h=500"
  ],
  "detailed_images": [
    "https://media.ulta.com/i/ulta/2643909?w=600&h=600&fmt=auto",
    "https://media.ulta.com/i/ulta/2643909_alt01?w=600&h=600&fmt=auto",
    "https://media.ulta.com/i/ulta/2643909_alt02?w=600&h=600&fmt=auto",
    "https://media.ulta.com/i/ulta/2643909_alt03?w=600&h=600&fmt=auto",
    "https://media.ulta.com/i/ulta/2643909_alt04?w=600&h=600&fmt=auto",
    "https://media.ulta.com/i/ulta/2643909_alt05?w=600&h=600&fmt=auto",
    "https://media.ulta.com/v/ulta/2643909_vid01/thumbs/94914f2a-0e03-4014-86b7-1d412aebc3a7?w=600&h=337&fmt=auto"
  ],
  "summary": "SummaryHighlightsClean IngredientsCruelty FreeSustainable PackagingGive BackINKEY The Breakout Set is a three-step skincare set suitable for acne-prone skin that unclogs pores, minimizes excess oil, and reduce the appearance of redness for clearer-looking skin.",
  "details": "DetailsBenefitsClearer skin starts here. This powerhouse trio of fast-acting skincare work together to target and visibly improve breakouts. From blemishes and blackheads to post-breakout dark spots this set supports you at every stage of your breakout journey.Clinical Results: In a 4-week independent consumer trial of 66 people using the Salicyclic Acid Cleanser: - 90% agree skin looks visibly clearer after 3 daysIn a 4-week independent consumer trial of 22 people using Succinic Acid Treatment: - 95% agree imperfections visibly improved in 12 hoursKey IngredientsSalicylic Acid 2% (Salicylic Acid Cleanser): Works intensely within pores to unclog and gently exfoliateSuccinic Acid 2% (Succinic Acid Treatment): Reduces the appearance of pimples and excess oilNiacinamide 10% (Niacinamide Serum): Reduces the appearance of excess oil, blemishes, and rednessIncludesSalicylic Acid Acne + Blackhead Cleanser (2.0 oz)Succinic Acid Acne Treatment (0.5 oz)Niacinamide Oil Control Serum (1.0 oz)Item 2643909How To UseSuggested Usage:Suitable for daily use as part of your morning or evening routine.Salicylic Acid Cleanser:Gently massage a small raspberry-size amount of Salicylic Acid Cleanser onto face and neck for at least 60 seconds.Rinse thoroughly.Succinic Acid Treatment:It can be applied directly to imperfection up to three times per day.Squeeze a small amount of Succinic Acid Treatment onto a clean finger and apply directly onto the area you wish to treat.Wait at least five minutes for the formula to dry before using other skincare or makeup on top.Niacinamide Serum:Gently pat a pea-size amount of Niacinamide Serum onto face and neck and follow with your preferred moisturizer.Always finish with SPF for your morning routine.IngredientsSalicylic Acid Acne + Blackhead Cleanser: Aqua (Water), Propanediol, Glycerin, Sodium Methyl Cocoyl Taurate, Cocamidopropyl Betaine, PEG-120 Methyl Glucose Dioleate, Salicylic Acid, PEG-150 Pentaerythrityl Tetrastearate, PEG-6 Caprylic/Capric Glycerides, Betaine, Zinc PCA, Phenoxyethanol, Sodium Chloride, Allantoin, Sodium Hydroxide, Coco-Glucoside, Glyceryl Oleate, Benzyl Alcohol, Coconut Acid, Ethylhexylglycerin, Sodium Benzoate, Citric Acid, Dehydroacetic Acid, Trisodium Ethylenediamine Disuccinate, Tocopherol, Hydrogenated Palm Glycerides Citrate.Succinic Acid Acne Treatment: Water (Aqua/Eau), Caprylic/Capric Triglyceride, Glyceryl Stearate SE, Stearic Acid, Cetearyl Alcohol, Colloidal Sulfur, Glycerin, Succinic Acid, Hydroxyethyl Acrylate/Sodium Acryloyldimethyl Taurate Copolymer, Salicylic Acid, Phenoxyethanol, Squalane, Benzyl Alcohol, Sodium Hyaluronate, Polysorbate 60, Ethylhexylglycerin, Sodium Hydroxide, Dehydroacetic Acid, Malachite Extract, Sorbitan Isostearate, Trisodium Ethylenediamine Disuccinate, CI 75810 (Chlorophyllin-Copper Complex).Niacinamide Oil Control Serum: Water (Aqua), Niacinamide,Glycerin, Propanediol, Butylene Glycol, Squalane, Leuconostoc/Radish Root Ferment Filtrate, Hyaluronic Acid, Phenoxyethanol, Hydroxyethyl Acrylate/Sodium Acryloyldimethyl Taurate Copolymer, Hydroxyethylcellulose, Phospholipids, Xanthan Gum, Glycine Soja (Soybean) Extract, Allantoin, Disodium Edta, Polysorbate 60, Panthenol, Glycolipids, Glycine Soja (Soybean) Sterol, Disodium Phosphate, Citric Acid, Sodium Phosphate.",
  "how_to_use": "Suggested Usage:Suitable for daily use as part of your morning or evening routine.Salicylic Acid Cleanser:Gently massage a small raspberry-size amount of Salicylic Acid Cleanser onto face and neck for at least 60 seconds.Rinse thoroughly.Succinic Acid Treatment:It can be applied directly to imperfection up to three times per day.Squeeze a small amount of Succinic Acid Treatment onto a clean finger and apply directly onto the area you wish to treat.Wait at least five minutes for the formula to dry before using other skincare or makeup on top.Niacinamide Serum:Gently pat a pea-size amount of Niacinamide Serum onto face and neck and follow with your preferred moisturizer.Always finish with SPF for your morning routine.",
  "ingredients": [
    "Salicylic Acid Acne + Blackhead Cleanser: Aqua (Water)",
    "Propanediol",
    "Glycerin",
    "Sodium Methyl Cocoyl Taurate",
    "Cocamidopropyl Betaine",
    "PEG-120 Methyl Glucose Dioleate",
    "Salicylic Acid",
    "PEG-150 Pentaerythrityl Tetrastearate",
    "PEG-6 Caprylic/Capric Glycerides",
    "Betaine",
    "Zinc PCA",
    "Phenoxyethanol",
    "Sodium Chloride",
    "Allantoin",
    "Sodium Hydroxide",
    "Coco-Glucoside",
    "Glyceryl Oleate",
    "Benzyl Alcohol",
    "Coconut Acid",
    "Ethylhexylglycerin",
    "Sodium Benzoate",
    "Citric Acid",
    "Dehydroacetic Acid",
    "Trisodium Ethylenediamine Disuccinate",
    "Tocopherol",
    "Hydrogenated Palm Glycerides Citrate.Succinic Acid Acne Treatment: Water (Aqua/Eau)",
    "Caprylic/Capric Triglyceride",
    "Glyceryl Stearate SE",
    "Stearic Acid",
    "Cetearyl Alcohol",
    "Colloidal Sulfur",
    "Glycerin",
    "Succinic Acid",
    "Hydroxyethyl Acrylate/Sodium Acryloyldimethyl Taurate Copolymer",
    "Salicylic Acid",
    "Phenoxyethanol",
    "Squalane",
    "Benzyl Alcohol",
    "Sodium Hyaluronate",
    "Polysorbate 60",
    "Ethylhexylglycerin",
    "Sodium Hydroxide",
    "Dehydroacetic Acid",
    "Malachite Extract",
    "Sorbitan Isostearate",
    "Trisodium Ethylenediamine Disuccinate",
    "Niacinamide",
    "Glycerin",
    "Propanediol",
    "Butylene Glycol",
    "Squalane",
    "Leuconostoc/Radish Root Ferment Filtrate",
    "Hyaluronic Acid",
    "Phenoxyethanol",
    "Hydroxyethyl Acrylate/Sodium Acryloyldimethyl Taurate Copolymer",
    "Hydroxyethylcellulose",
    "Phospholipids",
    "Xanthan Gum",
    "Glycine Soja (Soybean) Extract",
    "Allantoin",
    "Disodium Edta",
    "Polysorbate 60",
    "Panthenol",
    "Glycolipids",
    "Glycine Soja (Soybean) Sterol",
    "Disodium Phosphate",
    "Citric Acid",
    "Sodium Phosphate"
  ],
  "extended_contents": {},
  "tags": {
    "category": [
      "men",
      "mens"
    ],
    "product_type": [
      "serum",
      "mask",
      "treatment"
    ],
    "skin_type": [
      "oily",
      "dry",
      "acne-prone"
    ],
    "finish": [
      "sheer",
      "oil"
    ],
    "ingredients": [
      "hyaluronic-acid",
      "niacinamide",
      "salicylic-acid"
    ],
    "brand": [
      "mid-range",
      "mid-range"
    ],
    "special_features": [
      "cruelty-free",
      "spf"
    ]
  },
  "reviews": {
    "product_id": "pimprod2052476",
    "total_reviews": 2,
    "reviews": [],
    "paging": {
      "total_results": 0,
      "pages_total": 0,
      "page_size": 20,
      "current_page_number": 1
    },
    "rollup": {
      "properties": [],
      "rating_histogram": [
        0,
        0,
        0,
        1,
        1
      ],
      "review_histogram": [
        0,
        0,
        0,
        1,
        1
      ],
      "rating_count": 2,
      "review_count": 2,
      "average_rating": 4.5,
      "recommended_ratio": 0.0,
      "media": [],
      "native_review_count": 0,
      "native_sampling_review_count": 0,
      "native_sweepstakes_review_count": 0,
      "native_community_content_review_count": 0,
      "syndicated_review_count": 2,
      "locale": "en_US"
    }
  }
}