{
  "product_id": "pimprod2049650",
  "product_url": "https://www.ulta.com/p/hyaluronic-acid-low-ph-cleansing-foam-pimprod2049650",
  "extracted_at": "2025-09-23T04:10:16.738325+00:00",
  "product_name": "IsntreeHyaluronic Acid Low-pH Cleansing Foam",
  "brand": "Isntree",
  "categories": [
    "Home",
    "Skin Care",
    "Cleansers",
    "Face Wash"
  ],
  "category_keys": [
    "home",
    "skin-care",
    "cleansers",
    "face"
  ],
  "currency": "USD",
  "list_price": "20.00",
  "sale_price": "15.00",
  "availability": "in_stock",
  "rating_avg": "5",
  "rating_count": "1",
  "images": [
    "https://media.ulta.com/i/ulta/2636344?w=500&h=500"
  ],
  "detailed_images": [
    "https://media.ulta.com/i/ulta/2636344?w=600&h=600&fmt=auto",
    "https://media.ulta.com/i/ulta/2636344_alt01?w=600&h=600&fmt=auto",
    "https://media.ulta.com/i/ulta/2636344_alt02?w=600&h=600&fmt=auto",
    "https://media.ulta.com/i/ulta/2636344_alt03?w=600&h=600&fmt=auto",
    "https://media.ulta.com/i/ulta/2636344_alt04?w=600&h=600&fmt=auto",
    "https://media.ulta.com/i/ulta/2636344_alt05?w=600&h=600&fmt=auto",
    "https://media.ulta.com/i/ulta/2636344_alt06?w=600&h=600&fmt=auto",
    "https://media.ulta.com/i/ulta/2636344_alt07?w=600&h=600&fmt=auto",
    "https://media.ulta.com/v/ulta/2636344_vid01/thumbs/3dc970b2-77e9-4170-84e9-d01e36a9fcc3?w=600&h=337&fmt=auto"
  ],
  "summary": "SummaryIsntree Hyaluronic Acid Low-pH Cleansing Foam is a gentle yet effective cleanser that contains hyaluronic acid and moisturizing ingredients, helping to maintain hydration and leaving your skin feeling refreshed and moisturized after cleansing.",
  "details": "DetailsBenefitsNo More Dry Skin After Cleansing: 8 types of hyaluronic acid and 17 types of amino acids help protect and hydrate your skin, maintaining its health and moisture balance even after cleansing.Gentle & Barrier Protecting: Cleanses without irritation while helping to maintain the skin’s moisture barrier.Fragrance-Free: No fragrance, perfect for sensitive skin.FeaturesGentle Yet Effective: Removes impurities and makeup without causing irritation, perfect for daily use.Soft, Dense, and Creamy Foam: Offers a moisturizing finish with every wash.Low pH Formula (5.5-6.5): Helps maintain your skin’s natural protective barrier.Skin Safety Tested: Passed skin irritation, microorganism, and heavy metals tests.Key Ingredients8 Types of Hyaluronic Acid: A blend of small, medium, and large molecular hyaluronic acids forms a moisture shield that locks in hydration and prevents moisture loss after cleansing.17 Types of Amino Acids: As components of skin protein, they help smooth and soften skin texture through direct contact, while providing deep hydration from within.Item 2636344How To UseTake an appropriate amount of foam and gently massage in circular motions onto a wet face. Rinse thoroughly with warm water.IngredientsWater, Sodium Cocoyl Isethionate, Glycerin, Sodium Methyl Cocoyl Taurate, Glycol Distearate, Potassium Cocoate, Glycol Stearate, Potassium Cocoyl Glycinate, Laminaria Japonica Extract, Eclipta Prostrata Leaf Extract, Ulmus Davidiana Root Extract, Ficus Carica (Fig) Fruit Extract, Centella Asiatica Extract, Amaranthus Caudatus Seed Extract, Oryza Sativa (Rice) Bran Extract, Hydrogenated Lecithin, Sodium Hyaluronate, Sodium Chloride, Caprylyl/Capryl Glucoside, Citric Acid, Disodium Edta, Decylene Glycol, Butylene Glycol, Polyquaternium-39, Dipropylene Glycol, Fructooligosaccharides, Beta-Glucan, Panthenol, Ceramide Np, Hydrolyzed Hyaluronic Acid, Tocopherol, Allantoin, Hydroxypropyltrimonium Hyaluronate, Glycine, Sodium Hyaluronate Crosspolymer, Serine, Glutamic Acid, Hyaluronic Acid, Dipotassium Glycyrrhizate, Sodium Acetylated Hyaluronate, Aspartic Acid, Leucine, Lysine, Alanine, Arginine, Valine, Isoleucine, Threonine, Tyrosine, Phenylalanine, Proline, Histidine, Cysteine, Methionine, Hydrolyzed Sodium Hyaluronate, Potassium Hyaluronate, 1,2-Hexanediol, Hydroxyacetophenone, Ethylhexylglycerin, Sodium Benzoate, Pentylene Glycol, Caprylyl Glycol.",
  "how_to_use": "Take an appropriate amount of foam and gently massage in circular motions onto a wet face. Rinse thoroughly with warm water.",
  "ingredients": [
    "Water",
    "Sodium Cocoyl Isethionate",
    "Glycerin",
    "Sodium Methyl Cocoyl Taurate",
    "Glycol Distearate",
    "Potassium Cocoate",
    "Glycol Stearate",
    "Potassium Cocoyl Glycinate",
    "Laminaria Japonica Extract",
    "Eclipta Prostrata Leaf Extract",
    "Ulmus Davidiana Root Extract",
    "Ficus Carica (Fig) Fruit Extract",
    "Centella Asiatica Extract",
    "Amaranthus Caudatus Seed Extract",
    "Oryza Sativa (Rice) Bran Extract",
    "Hydrogenated Lecithin",
    "Sodium Hyaluronate",
    "Sodium Chloride",
    "Caprylyl/Capryl Glucoside",
    "Citric Acid",
    "Disodium Edta",
    "Decylene Glycol",
    "Butylene Glycol",
    "Polyquaternium-39",
    "Dipropylene Glycol",
    "Fructooligosaccharides",
    "Beta-Glucan",
    "Panthenol",
    "Ceramide Np",
    "Hydrolyzed Hyaluronic Acid",
    "Tocopherol",
    "Allantoin",
    "Hydroxypropyltrimonium Hyaluronate",
    "Glycine",
    "Sodium Hyaluronate Crosspolymer",
    "Serine",
    "Glutamic Acid",
    "Hyaluronic Acid",
    "Dipotassium Glycyrrhizate",
    "Sodium Acetylated Hyaluronate",
    "Aspartic Acid",
    "Leucine",
    "Lysine",
    "Alanine",
    "Arginine",
    "Valine",
    "Isoleucine",
    "Threonine",
    "Tyrosine",
    "Phenylalanine",
    "Proline",
    "Histidine",
    "Cysteine",
    "Methionine",
    "Hydrolyzed Sodium Hyaluronate",
    "Potassium Hyaluronate",
    "2-Hexanediol",
    "Hydroxyacetophenone",
    "Ethylhexylglycerin",
    "Sodium Benzoate",
    "Pentylene Glycol",
    "Caprylyl Glycol"
  ],
  "extended_contents": {},
  "tags": {
    "category": [
      "face"
    ],
    "product_type": [
      "cleanser"
    ],
    "skin_type": [
      "dry",
      "sensitive"
    ],
    "finish": [
      "creamy",
      "cream",
      "foam"
    ],
    "ingredients": [
      "hyaluronic-acid",
      "ceramides"
    ],
    "brand": [
      "mid-range",
      "affordable"
    ],
    "special_features": [
      "natural",
      "fragrance-free",
      "hydrating",
      "soothing",
      "purifying"
    ]
  },
  "reviews": {
    "product_id": "pimprod2049650",
    "total_reviews": 1,
    "reviews": [
      {
        "review_id": 558379054,
        "rating": 5,
        "headline": "LOVE LOVE LOVE",
        "comments": "makes my skin feels so hydrated and plumped, probably the best cleanser ive ever used. it also foams up nicely! little goes a long way, cleanses my makeup pretty good as well",
        "nickname": "maeva",
        "location": "San diego",
        "created_date": 1753639023213,
        "bottom_line": null,
        "helpful_votes": 0,
        "not_helpful_votes": 0
      }
    ],
    "paging": {
      "total_results": 1,
      "pages_total": 1,
      "page_size": 20,
      "current_page_number": 1
    },
    "rollup": {
      "properties": [],
      "rating_histogram": [
        0,
        0,
        0,
        0,
        1
      ],
      "review_histogram": [
        0,
        0,
        0,
        0,
        1
      ],
      "rating_count": 1,
      "review_count": 1,
      "average_rating": 5.0,
      "recommended_ratio": 0.0,
      "media": [],
      "name": "Hyaluronic Acid Low-pH Cleansing Foam",
      "native_review_count": 1,
      "native_sampling_review_count": 0,
      "native_sweepstakes_review_count": 0,
      "native_community_content_review_count": 0,
      "syndicated_review_count": 0,
      "locale": "en_US"
    }
  }
}