{
  "product_id": "pimprod2044690",
  "product_url": "https://www.ulta.com/p/on-glow-gift-set-pimprod2044690",
  "extracted_at": "2025-09-23T04:44:38.803594+00:00",
  "product_name": "Kate SomervilleOn-The-Glow Gift Set",
  "brand": "Kate Somerville",
  "categories": [
    "Home",
    "Skin Care",
    "Treatment & Serums",
    "Face Peels & Exfoliators"
  ],
  "category_keys": [
    "home",
    "skin-care",
    "men",
    "face"
  ],
  "currency": "USD",
  "list_price": "",
  "sale_price": "30.00",
  "availability": "in_stock",
  "rating_avg": "3.6",
  "rating_count": "5",
  "images": [
    "https://media.ulta.com/i/ulta/2625430?w=500&h=500"
  ],
  "detailed_images": [
    "https://media.ulta.com/i/ulta/2625430?w=600&h=600&fmt=auto",
    "https://media.ulta.com/i/ulta/2625430_alt01?w=600&h=600&fmt=auto",
    "https://media.ulta.com/i/ulta/2625430_alt02?w=600&h=600&fmt=auto",
    "https://media.ulta.com/i/ulta/2625430_alt03?w=600&h=600&fmt=auto",
    "https://media.ulta.com/i/ulta/2625430_alt04?w=600&h=600&fmt=auto",
    "https://media.ulta.com/i/ulta/2625430_alt05?w=600&h=600&fmt=auto",
    "https://media.ulta.com/i/ulta/2625430_alt06?w=600&h=600&fmt=auto",
    "https://media.ulta.com/i/ulta/2625430_alt07?w=600&h=600&fmt=auto"
  ],
  "summary": "SummaryKate Somerville's On-The-Glow Gift Set their best-selling, pore-improving glow stars are all wrapped up in major savings. Skin-transforming heroes for glowing skin from head-to-toe. Get fresh-from-the-spa radiance with these clinically proven glow boosters for softer, smoother, healthy glowing skin.",
  "details": "DetailsBenefitsExfoliKate Intensive Exfoliating Treatment - Smooth skin texture and minimize appearance of poresExfoliKate Cleanser Daily Foaming Wash - Effectively cleanses away dirt, oil, makeup and other impurities while gently exfoliating to reveal softer, smoother, glowing skin.ExfoliKate Glow Moisturizer - Revive dull, dry, lackluster-looking skin while also going deep into skin for dewy, refreshed, radiant results.Key IngredientsPineapple, Pumpkin + Papaya Enzymes : Gently exfoliate without over-drying, leaving skin feeling soft and moisturized in ExfoliKate® Cleanser Daily Foaming Wash, ExfoliKate® Intensive Exfoliating Treatment and ExfoliKate® Glow Moisturizer.Aloe Vera + Honey : Help soothe and condition skin in ExfoliKate® Intensive Exfoliating Treatment.Silica : A natural exfoliant that “physically” exfoliates skin in ExfoliKate® Intensive Exfoliating Treatment.Glycolic + Lactic Acid: Refine the appearance of pores and help clear buildup on skin's surface in ExfoliKate® Cleanser Daily Foaming Wash and ExfoliKate® Glow Moisturizer.IncludesExfoliKate Intensive Exfoliating Treatment (0.5 oz)ExfoliKate Cleanser Daily Foaming Wash (1.7 oz)ExfoliKate Glow Moisturizer (0.5 oz)Item 2625430How To UseExfoliKate Intensive Exfoliating Treatment: AM or PM. Use once or twice a week. Apply a thin, even layer to a clean, wet face, massaging in a circular motion for 30 seconds. Leave on for up to 2 minutes. Rinse and gently pat dry. This product may cause the skin to tingle and flush slightly for a short time. For sensitive skin, leave on for less than 1 minute. In case of skin irritation discontinue use.ExfoliKate Cleanser Daily Foaming Wash: Use AM and PM. Apply a small amount to wet face and neck and massage gently for 30 seconds. Rinse and gently pat dry. For optimal results, swap out and use ExfoliKate Intensive Exfoliating Treatment twice a week in the shower.ExfoliKate Glow Moisturizer: Use AM or PM. Apply a thin, even layer to face and neck. Use alone or layer over your favorite Kate Somerville serum.IngredientsExfoliKate Cleanser Daily Foaming Wash: Aqua/Water/Eau, Stearic Acid, Sodium Cocoyl Glycinate, Lauramidopropyl Betaine, Glycerin, Hydroxypropyl Starch Phosphate, CetearylPhosphate, Xylitylglucoside, Dimethicone PEG-8 Meadowfoamate, Anhydroxylitol, Xylitol, Leuconostoc/Radish Root Ferment Filtrate, Bromelain, Papain, Lactobacillus/Pumpkin Fruit Ferment Filtrate, Lauramide DIPA, Aloe Barbadensis Leaf Juice Powder, Lactic Acid, Glycolic Acid, Citrus Aurantium Bergamia (Bergamot) Fruit Oil, Aniba Rosaeodora (Rosewood) Wood Extract, Citrus Aurantium Dulcis (Orange) Peel Oil, Glucose, Pelargonium Graveolens Flower Oil,Citral, Benzyl Benzoate, Benzyl Alcohol, Sodium Hydroxide, Limonene, Chlorphenesin, Linalool,Citronellol, Maltodextrin, Geraniol,CI 75810(Chlorophyllin-CopperComplex).ExfoliKate Intensive Exfoliating Treatment: Aqua/Water/Eau, Lactic Acid, Silica, Glycine Soja (Soybean) Oil, Pectin, Cetearyl Alcohol, Carica Papaya (Papaya) Fruit, Ceteareth-20, Cetyl Alcohol, Phenoxyethanol, Dehydroxanthan Gum, Glyceryl Stearate, PEG-100 Stearate, Salicylic Acid, Lactobacillus/Pumpkin Ferment Extract, Alcohol Denat., Sorbic Acid, Cinnamal, Mel/Honey/Miel, Citrus Aurantium Bergamia (Bergamot) Fruit Oil, Eugenol, Potassium Sorbate, Limonene, Linalool, Lavandula Angustifolia (Lavender) Oil, Beta-Carotene, Aloe Barbadensis Leaf Juice Powder, Bromelain, Papain, Retinyl Palmitate, Tocopheryl Acetate, Cinnamomum Cassia Leaf Oil, Acetic Acid, Pogostemon Cablin Oil, Pelargonium Graveolens Flower Oil, Aniba Rosaeodora (Rosewood) Wood Extract, Citrus Aurantium Dulcis (Orange) Peel Oil, CI 75810 (Chlorophyllin-Copper Complex).ExfoliKate Glow Moisturizer: Water/Aqua/Eau, Cetyl Ricinoleate, Isostearyl Palmitate, Dimethicone, Squalane, Lactic Acid, Glyceryl Stearate, PEG-100 Stearate, Propanediol, Glycolic Acid, Myristyl Alcohol, Cyclopentasiloxane, Sodium Hydroxide, Lactobacillus/Pumpkin Fruit Ferment Filtrate, Leuconostoc/Radish Root Ferment Filtrate, Bromelain, Papain, Opuntia Ficus-Indica Fruit Extract, Glycerin, Saccharomyces Cerevisiae Extract, Polysilicone-11, Citrus Aurantium Bergamia (Bergamot) Fruit Oil, Aniba Rosaeodora (Rosewood) Wood Extract, Citrus Aurantium Dulcis (Orange) Peel Oil, Geranium Maculatum Oil, Tocopheryl Acetate, Phenoxyethanol, Polyacrylate Crosspolymer-6, Myristyl Glucoside, Cyclohexasiloxane, PEG-40 Stearate, Xanthan Gum, Ethylhexylglycerin, Disodium EDTA, Maltodextrin, Chlorophyllin-Copper Complex, T-Butyl Alcohol, Citronellol, Benzyl Benzoate, Citral, Limonene, Linalool.Shipping & Coupon RestrictionsThis brand is excluded from most Ulta Beauty coupons.See brand eligibility details",
  "how_to_use": "ExfoliKate Intensive Exfoliating Treatment: AM or PM. Use once or twice a week. Apply a thin, even layer to a clean, wet face, massaging in a circular motion for 30 seconds. Leave on for up to 2 minutes. Rinse and gently pat dry. This product may cause the skin to tingle and flush slightly for a short time. For sensitive skin, leave on for less than 1 minute. In case of skin irritation discontinue use.ExfoliKate Cleanser Daily Foaming Wash: Use AM and PM. Apply a small amount to wet face and neck and massage gently for 30 seconds. Rinse and gently pat dry. For optimal results, swap out and use ExfoliKate Intensive Exfoliating Treatment twice a week in the shower.ExfoliKate Glow Moisturizer: Use AM or PM. Apply a thin, even layer to face and neck. Use alone or layer over your favorite Kate Somerville serum.",
  "ingredients": [
    "ExfoliKate Cleanser Daily Foaming Wash: Aqua/Water/Eau",
    "Stearic Acid",
    "Sodium Cocoyl Glycinate",
    "Lauramidopropyl Betaine",
    "Glycerin",
    "Hydroxypropyl Starch Phosphate",
    "CetearylPhosphate",
    "Xylitylglucoside",
    "Dimethicone PEG-8 Meadowfoamate",
    "Anhydroxylitol",
    "Xylitol",
    "Leuconostoc/Radish Root Ferment Filtrate",
    "Bromelain",
    "Papain",
    "Lactobacillus/Pumpkin Fruit Ferment Filtrate",
    "Lauramide DIPA",
    "Aloe Barbadensis Leaf Juice Powder",
    "Lactic Acid",
    "Glycolic Acid",
    "Citrus Aurantium Bergamia (Bergamot) Fruit Oil",
    "Aniba Rosaeodora (Rosewood) Wood Extract",
    "Citrus Aurantium Dulcis (Orange) Peel Oil",
    "Glucose",
    "Pelargonium Graveolens Flower Oil",
    "Citral",
    "Benzyl Benzoate",
    "Benzyl Alcohol",
    "Sodium Hydroxide",
    "Limonene",
    "Chlorphenesin",
    "Linalool",
    "Citronellol",
    "Maltodextrin",
    "Geraniol",
    "Lactic Acid",
    "Silica",
    "Glycine Soja (Soybean) Oil",
    "Pectin",
    "Cetearyl Alcohol",
    "Carica Papaya (Papaya) Fruit",
    "Ceteareth-20",
    "Cetyl Alcohol",
    "Phenoxyethanol",
    "Dehydroxanthan Gum",
    "Glyceryl Stearate",
    "PEG-100 Stearate",
    "Salicylic Acid",
    "Lactobacillus/Pumpkin Ferment Extract",
    "Alcohol Denat",
    "Sorbic Acid",
    "Cinnamal",
    "Mel/Honey/Miel",
    "Citrus Aurantium Bergamia (Bergamot) Fruit Oil",
    "Eugenol",
    "Potassium Sorbate",
    "Limonene",
    "Linalool",
    "Lavandula Angustifolia (Lavender) Oil",
    "Beta-Carotene",
    "Aloe Barbadensis Leaf Juice Powder",
    "Bromelain",
    "Papain",
    "Retinyl Palmitate",
    "Tocopheryl Acetate",
    "Cinnamomum Cassia Leaf Oil",
    "Acetic Acid",
    "Pogostemon Cablin Oil",
    "Pelargonium Graveolens Flower Oil",
    "Aniba Rosaeodora (Rosewood) Wood Extract",
    "Citrus Aurantium Dulcis (Orange) Peel Oil",
    "Cetyl Ricinoleate",
    "Isostearyl Palmitate",
    "Dimethicone",
    "Squalane",
    "Lactic Acid",
    "Glyceryl Stearate",
    "PEG-100 Stearate",
    "Propanediol",
    "Glycolic Acid",
    "Myristyl Alcohol",
    "Cyclopentasiloxane",
    "Sodium Hydroxide",
    "Lactobacillus/Pumpkin Fruit Ferment Filtrate",
    "Leuconostoc/Radish Root Ferment Filtrate",
    "Bromelain",
    "Papain",
    "Opuntia Ficus-Indica Fruit Extract",
    "Glycerin",
    "Saccharomyces Cerevisiae Extract",
    "Polysilicone-11",
    "Citrus Aurantium Bergamia (Bergamot) Fruit Oil",
    "Aniba Rosaeodora (Rosewood) Wood Extract",
    "Citrus Aurantium Dulcis (Orange) Peel Oil",
    "Geranium Maculatum Oil",
    "Tocopheryl Acetate",
    "Phenoxyethanol",
    "Polyacrylate Crosspolymer-6",
    "Myristyl Glucoside",
    "Cyclohexasiloxane",
    "PEG-40 Stearate",
    "Xanthan Gum",
    "Ethylhexylglycerin",
    "Disodium EDTA",
    "Maltodextrin",
    "Chlorophyllin-Copper Complex",
    "T-Butyl Alcohol",
    "Citronellol",
    "Benzyl Benzoate",
    "Citral",
    "Limonene",
    "Linalool"
  ],
  "extended_contents": {},
  "tags": {
    "category": [
      "men",
      "face",
      "mens"
    ],
    "product_type": [
      "serum",
      "mask",
      "treatment",
      "peel"
    ],
    "skin_type": [
      "dry",
      "sensitive"
    ],
    "finish": [
      "matte",
      "dewy",
      "sheer",
      "creamy",
      "powdery",
      "oil",
      "foam"
    ],
    "ingredients": [
      "salicylic-acid",
      "glycolic-acid",
      "lactic-acid"
    ],
    "brand": [
      "mid-range",
      "mid-range"
    ],
    "special_features": [
      "natural",
      "exfoliating",
      "brightening"
    ]
  },
  "reviews": {
    "product_id": "pimprod2044690",
    "total_reviews": 5,
    "reviews": [
      {
        "review_id": 542207767,
        "rating": 2,
        "headline": "Description isn't accurate",
        "comments": "The package comes with .5 fl oz of the exfoliating treatment and glow moisturizer and 1.7 fl oz of the foaming wash. The description is false and wouldnt have purchased it if it was labeled correctly.",
        "nickname": "Misleading",
        "location": "Chicago",
        "created_date": 1735953196367,
        "bottom_line": null,
        "helpful_votes": 15,
        "not_helpful_votes": 7
      },
      {
        "review_id": 539398985,
        "rating": 5,
        "headline": "In love ❤️ with this set.",
        "comments": "Buy it for yourself and your friends and family.",
        "nickname": "KittyKat",
        "location": "NWI",
        "created_date": 1733922550951,
        "bottom_line": null,
        "helpful_votes": 3,
        "not_helpful_votes": 3
      },
      {
        "review_id": 537303972,
        "rating": 5,
        "headline": "Very Impressed",
        "comments": "I bought the sample version to make sure it wouldn't go in my junk drawer and this one was a keeper. Cleanser feels clean w/o stripping. The extolment stings and works! The moisturizer also stings a bit but feels great on! Sensitive skin beware.",
        "nickname": "shirley",
        "location": "LR",
        "created_date": 1730744721991,
        "bottom_line": "Yes",
        "helpful_votes": 5,
        "not_helpful_votes": 1
      },
      {
        "review_id": 537200937,
        "rating": 5,
        "headline": "Love ExfoliKate products",
        "comments": "This is a great deal! Yes, the one product is smaller than they said in the details, but all of these still last a long time. The face wash has a really nice light citrus smell. I havent used the moisturizer yet because I couldnt read what it was exactly or when to use it (before looking it up) because the white writing on the transparent container was impossible to read on top of being partially rubbed off. So thats my only complaint.",
        "nickname": "BeeGeeNC",
        "location": "Brevard, NC",
        "created_date": 1730557005007,
        "bottom_line": null,
        "helpful_votes": 2,
        "not_helpful_votes": 3
      },
      {
        "review_id": 536542911,
        "rating": 1,
        "headline": "Not as described NOT happy",
        "comments": "Said the intense exfoliating treatment is a 1.7 Oz in description.  That is a lie.   It is only .05 Oz.   Not pleased. Want want I thought I ordered or a refund",
        "nickname": "Ami",
        "location": "Texas",
        "created_date": 1729638656336,
        "bottom_line": "No",
        "helpful_votes": 18,
        "not_helpful_votes": 7
      }
    ],
    "paging": {
      "total_results": 5,
      "pages_total": 1,
      "page_size": 20,
      "current_page_number": 1
    },
    "rollup": {
      "properties": [],
      "rating_histogram": [
        1,
        1,
        0,
        0,
        3
      ],
      "review_histogram": [
        1,
        1,
        0,
        0,
        3
      ],
      "rating_count": 5,
      "review_count": 5,
      "average_rating": 3.6,
      "recommended_ratio": 0.5,
      "media": [],
      "name": "On-The-Glow Gift Set",
      "native_review_count": 5,
      "native_sampling_review_count": 0,
      "native_sweepstakes_review_count": 0,
      "native_community_content_review_count": 0,
      "syndicated_review_count": 0,
      "locale": "en_US"
    }
  }
}