{
  "product_id": "pimprod2054260",
  "product_url": "https://www.ulta.com/p/madecassoside-moisture-calming-cleanser-pimprod2054260",
  "extracted_at": "2025-09-23T04:28:22.600119+00:00",
  "product_name": "MEDIHEALMadecassoside Moisture Calming Cleanser",
  "brand": "MEDIHEAL",
  "categories": [
    "Home",
    "Skin Care",
    "Cleansers",
    "Face Wash"
  ],
  "category_keys": [
    "home",
    "skin-care",
    "cleansers",
    "face"
  ],
  "currency": "USD",
  "list_price": "",
  "sale_price": "12.00",
  "availability": "in_stock",
  "rating_avg": "",
  "rating_count": "",
  "images": [
    "https://media.ulta.com/i/ulta/2648309?w=500&h=500"
  ],
  "detailed_images": [
    "https://media.ulta.com/i/ulta/2648309?w=600&h=600&fmt=auto",
    "https://media.ulta.com/i/ulta/2648309_alt01?w=600&h=600&fmt=auto",
    "https://media.ulta.com/i/ulta/2648309_alt02?w=600&h=600&fmt=auto",
    "https://media.ulta.com/i/ulta/2648309_alt03?w=600&h=600&fmt=auto",
    "https://media.ulta.com/i/ulta/2648309_alt04?w=600&h=600&fmt=auto",
    "https://media.ulta.com/i/ulta/2648309_alt05?w=600&h=600&fmt=auto"
  ],
  "summary": "SummaryMediheal's Madecassoside Moisture Calming Cleanser gently yet effectively removes impurities while soothing and hydrating skin. Infused with madecassoside for calming care, it leaves the skin soft, refresed, and comfortable after cleansing.",
  "details": "DetailsBenefitsGently yet effectively removing impurities with triple pore-deep cleansing, it delivers instant soothing hydration for soft, comfortable skin without tightness, making it ideal for dry or sensitive skin in need of calming care.Having completed a skin irritation test for sensitive skin and certified by Germany Dermatest, this mildly alkaline formula offers a refreshing greenery scent.With its dense whipped-cream foam, it gently deep cleanses using fine, tightly packed micro-bubbles.Key IngredientsMadecassoside Liposome - Helps soothe and protect the skin's moisture barrierPanthenol + Triple Hyaluronic Acid - Replenishes and locks in moisturePapain - Supports gentle exfoliation and keratin careResearch ResultsMoisture retention improvement: +105.66%Deep pore cleansing: 99.49% improvement after cleansingSebum removal inside pores: 112.08% improvement after useItem 2648309How To UseAdd water to create a creamy foam, gently massage onto the face, then rinse. Suitable for daily facial cleansing.IngredientsWater, Glycerin, Hydrogenated Palm Acid, Potassium Hydroxide, Potassium Cocoyl Glycinate, Potassium Cocoate, Glyceryl Stearate, Polyquaternium-7, Acrylates/C10-30 Alkyl Acrylate Crosspolymer, Pyrus Communis (Pear) Fruit Extract, Juniperus Virginiana Oil, Rosa Damascena Flower Water, Sodium Phytate, Cucumis Melo (Melon) Fruit Extract, Iris Florentina Root Extract, Simmondsia Chinensis (Jojoba) Seed Oil, Hedera Helix (Ivy) Leaf/Stem Extract, Pogostemon Cablin Oil, Sodium Benzoate, Artemisia Vulgaris Oil, Rosmarinus Officinalis (Rosemary) Leaf Oil, Betaine, Hydrolyzed Hyaluronic Acid, Hydrolyzed Sodium Hyaluronate, Panthenol, Papain, Sodium Hyaluronate, Butylene Glycol, Madecassoside, Lecithin, 1,2-Hexanediol.",
  "how_to_use": "Add water to create a creamy foam, gently massage onto the face, then rinse. Suitable for daily facial cleansing.",
  "ingredients": [
    "Water",
    "Glycerin",
    "Hydrogenated Palm Acid",
    "Potassium Hydroxide",
    "Potassium Cocoyl Glycinate",
    "Potassium Cocoate",
    "Glyceryl Stearate",
    "Polyquaternium-7",
    "Acrylates/C10-30 Alkyl Acrylate Crosspolymer",
    "Pyrus Communis (Pear) Fruit Extract",
    "Juniperus Virginiana Oil",
    "Rosa Damascena Flower Water",
    "Sodium Phytate",
    "Cucumis Melo (Melon) Fruit Extract",
    "Iris Florentina Root Extract",
    "Simmondsia Chinensis (Jojoba) Seed Oil",
    "Hedera Helix (Ivy) Leaf/Stem Extract",
    "Pogostemon Cablin Oil",
    "Sodium Benzoate",
    "Artemisia Vulgaris Oil",
    "Rosmarinus Officinalis (Rosemary) Leaf Oil",
    "Betaine",
    "Hydrolyzed Hyaluronic Acid",
    "Hydrolyzed Sodium Hyaluronate",
    "Panthenol",
    "Papain",
    "Sodium Hyaluronate",
    "Butylene Glycol",
    "Madecassoside",
    "Lecithin",
    "2-Hexanediol"
  ],
  "extended_contents": {},
  "tags": {
    "category": [
      "face"
    ],
    "product_type": [
      "cleanser"
    ],
    "skin_type": [
      "dry",
      "sensitive"
    ],
    "finish": [
      "creamy",
      "cream",
      "oil",
      "foam"
    ],
    "ingredients": [
      "hyaluronic-acid"
    ],
    "brand": [
      "mid-range",
      "affordable"
    ],
    "special_features": [
      "hydrating",
      "soothing",
      "purifying"
    ]
  },
  "reviews": {
    "product_id": "pimprod2054260",
    "total_reviews": 0,
    "reviews": [],
    "paging": {
      "total_results": 0,
      "pages_total": 0,
      "page_size": 20,
      "current_page_number": 1
    },
    "rollup": {}
  }
}