{
  "product_id": "pimprod2053544",
  "product_url": "https://www.ulta.com/p/pdrn-pink-niacinamide-milky-toner-pimprod2053544",
  "extracted_at": "2025-09-23T04:46:23.526998+00:00",
  "product_name": "medicubePDRN Pink Niacinamide Milky Toner",
  "brand": "medicube",
  "categories": [
    "Home",
    "Skin Care",
    "Cleansers",
    "Toner"
  ],
  "category_keys": [
    "home",
    "skin-care",
    "cleansers",
    "toner"
  ],
  "currency": "USD",
  "list_price": "",
  "sale_price": "21.00",
  "availability": "in_stock",
  "rating_avg": "5",
  "rating_count": "2",
  "images": [
    "https://media.ulta.com/i/ulta/2645361?w=500&h=500"
  ],
  "detailed_images": [
    "https://media.ulta.com/i/ulta/2645361?w=600&h=600&fmt=auto",
    "https://media.ulta.com/i/ulta/2645361_alt01?w=600&h=600&fmt=auto",
    "https://media.ulta.com/i/ulta/2645361_alt02?w=600&h=600&fmt=auto",
    "https://media.ulta.com/i/ulta/2645361_alt03?w=600&h=600&fmt=auto",
    "https://media.ulta.com/i/ulta/2645361_alt04?w=600&h=600&fmt=auto",
    "https://media.ulta.com/i/ulta/2645361_alt05?w=600&h=600&fmt=auto"
  ],
  "summary": "SummaryMedicube's PDRN Pink Niacinamide Milky Toner for dewy and moisturizing skin with pink glow for acne-prone skin. Deliver moisture to all skin layers, achieving glowy and dewy skin.",
  "details": "DetailsBenefitsBoosts hydration & dewiness – Increases moisture by 48% over 2 weeks, leaving skin plump and glowyBalances tone & soothes – Salmon DNA PDRN and niacinamide even out discoloration while calming sensitive skinStrengthens skin barrier – Ceramides, peptides, and PDRN fortify skin’s resilience and prevent moisture lossFeaturesMilky, lightweight texture – Absorbs quickly without stickiness—delivers hydration into all skin layersNon-comedogenic & dermatologist-tested – Safe for all skin types, including acne-prone and sensitive skinClean, pink glow formula – Contains Salmon DNA PDRN, niacinamide, ceramide, and peptide for radiant, glass-skin finishResearch ResultsImprovement in hydration 48.3% after 2 weeks of useImprovement in skin texture 6.59% after 2 weeks of useImprovement in uneven skin tone 2.7% after 2 weeks of use*Result may vary among individuals *Clinical Trial Tested by the 'Global Institute of Dermatological Sciences' / Results may vary depending on individual skin types.Item 2645361How To UseApply appropriate amount of PDRN Pink Niacinamide Milky Toner across entire face after cleansing.Tap gently to enhance absorption.Pro tip! To enhance results, recommend pairing this toner with our PDRN Pink Peptide Glow Serum.For external use only. Discontinue use if irritation occurs. Keep out of reach of children. *Read instructions and caution before use.IngredientsWater(Aqua), Glycerin, Niacinamide, Cetyl Ethylhexanoate, Caprylic/Capric Triglyceride, 1,2-Hexanediol, Pentaerythrityl Tetraethylhexanoate, Ethylhexyl Palmitate, Polyglyceryl-3 Distearate, Octyldodecanol, Diisostearyl Malate, C12-14 Alketh-12, Acrylates/C10-30 Alkyl Acrylate Crosspolymer, Tromethamine, Glyceryl Stearate, Ethylhexylglycerin, Trehalose, Glyceryl Stearate Citrate, Adenosine, Disodium EDTA, Cyanocobalamin, Saccharide Hydrolysate, Oryza Sativa (Rice) Bran Oil, Oryza Sativa (Rice) Bran Water, Butylene Glycol, Prunus Amygdalus Amara (Bitter Almond) Kernel Oil, Camellia Sinensis Leaf Extract, Pyrus Malus (Apple) Leaf Extract, Sorbitol, Panthenol, Propanediol, Vanilla Planifolia Fruit Extract, Jasminum Officinale (Jasmine) Flower Water, Xylitylglucoside, Anhydroxylitol, Helianthus Annuus (Sunflower) Seed Oil, Dipropylene Glycol, Sucrose Stearate, Xylitol, Beta-Carotene, Sodium DNA, Polyglyceryl-10 Oleate, Vaccinium Myrtillus Fruit Extract, Centella Asiatica Root Extract, Centella Asiatica Leaf Extract, Centella Asiatica Extract, Tocopherol, Pueraria Lobata Root Extract, Pentylene Glycol, Madecassoside, Milk Protein Extract, Lycopodium Clavatum Extract, Equisetum Arvense Extract, Phragmites Communis Extract, Prunus Amygdalus Dulcis (Sweet Almond) Fruit Extract, Lecithin, Tremella Fuciformis (Mushroom) Extract, Tabebuia Impetiginosa Bark Extract, Trifolium Pratense (Clover) Extract, Acetyl Glutamine, Asiatic Acid, Bacillus/Soybean Ferment Extract, Madecassic Acid, Asiaticoside, Hydrolyzed Wheat Protein, Hydrolyzed Soy Protein, Hydrolyzed Rice Protein, Hydrolyzed Rice Bran Protein, Hydrolyzed Corn Protein, Caprylyl Glycol, Sodium Hyaluronate, Folic Acid, Palmitoyl Pentapeptide-4, Ceramide NS, Ceramide NP, Ceramide EOP, Ceramide AP, Oligopeptide-3, Oligopeptide-2, Oligopeptide-1, Hexapeptide-11.Shipping & Coupon RestrictionsThis brand is excluded from most Ulta Beauty coupons.See brand eligibility details",
  "how_to_use": "Apply appropriate amount of PDRN Pink Niacinamide Milky Toner across entire face after cleansing.Tap gently to enhance absorption.Pro tip! To enhance results, recommend pairing this toner with our PDRN Pink Peptide Glow Serum.For external use only. Discontinue use if irritation occurs. Keep out of reach of children. *Read instructions and caution before use.",
  "ingredients": [
    "Water(Aqua)",
    "Glycerin",
    "Niacinamide",
    "Cetyl Ethylhexanoate",
    "Caprylic/Capric Triglyceride",
    "2-Hexanediol",
    "Pentaerythrityl Tetraethylhexanoate",
    "Ethylhexyl Palmitate",
    "Polyglyceryl-3 Distearate",
    "Octyldodecanol",
    "Diisostearyl Malate",
    "C12-14 Alketh-12",
    "Acrylates/C10-30 Alkyl Acrylate Crosspolymer",
    "Tromethamine",
    "Glyceryl Stearate",
    "Ethylhexylglycerin",
    "Trehalose",
    "Glyceryl Stearate Citrate",
    "Adenosine",
    "Disodium EDTA",
    "Cyanocobalamin",
    "Saccharide Hydrolysate",
    "Oryza Sativa (Rice) Bran Oil",
    "Oryza Sativa (Rice) Bran Water",
    "Butylene Glycol",
    "Prunus Amygdalus Amara (Bitter Almond) Kernel Oil",
    "Camellia Sinensis Leaf Extract",
    "Pyrus Malus (Apple) Leaf Extract",
    "Sorbitol",
    "Panthenol",
    "Propanediol",
    "Vanilla Planifolia Fruit Extract",
    "Jasminum Officinale (Jasmine) Flower Water",
    "Xylitylglucoside",
    "Anhydroxylitol",
    "Helianthus Annuus (Sunflower) Seed Oil",
    "Dipropylene Glycol",
    "Sucrose Stearate",
    "Xylitol",
    "Beta-Carotene",
    "Sodium DNA",
    "Polyglyceryl-10 Oleate",
    "Vaccinium Myrtillus Fruit Extract",
    "Centella Asiatica Root Extract",
    "Centella Asiatica Leaf Extract",
    "Centella Asiatica Extract",
    "Tocopherol",
    "Pueraria Lobata Root Extract",
    "Pentylene Glycol",
    "Madecassoside",
    "Milk Protein Extract",
    "Lycopodium Clavatum Extract",
    "Equisetum Arvense Extract",
    "Phragmites Communis Extract",
    "Prunus Amygdalus Dulcis (Sweet Almond) Fruit Extract",
    "Lecithin",
    "Tremella Fuciformis (Mushroom) Extract",
    "Tabebuia Impetiginosa Bark Extract",
    "Trifolium Pratense (Clover) Extract",
    "Acetyl Glutamine",
    "Asiatic Acid",
    "Bacillus/Soybean Ferment Extract",
    "Madecassic Acid",
    "Asiaticoside",
    "Hydrolyzed Wheat Protein",
    "Hydrolyzed Soy Protein",
    "Hydrolyzed Rice Protein",
    "Hydrolyzed Rice Bran Protein",
    "Hydrolyzed Corn Protein",
    "Caprylyl Glycol",
    "Sodium Hyaluronate",
    "Folic Acid",
    "Palmitoyl Pentapeptide-4",
    "Ceramide NS",
    "Ceramide NP",
    "Ceramide EOP",
    "Ceramide AP",
    "Oligopeptide-3",
    "Oligopeptide-2",
    "Oligopeptide-1",
    "Hexapeptide-11"
  ],
  "extended_contents": {},
  "tags": {
    "product_type": [
      "cleanser",
      "toner"
    ],
    "skin_type": [
      "dry",
      "sensitive",
      "acne-prone",
      "all skin types"
    ],
    "finish": [
      "dewy",
      "sheer",
      "oil"
    ],
    "color": [
      "pink"
    ],
    "ingredients": [
      "niacinamide",
      "peptides",
      "ceramides"
    ],
    "brand": [
      "mid-range",
      "affordable"
    ],
    "special_features": [
      "dermatologist-tested",
      "non-comedogenic",
      "hydrating",
      "brightening",
      "soothing",
      "purifying"
    ],
    "category": []
  },
  "reviews": {
    "product_id": "pimprod2053544",
    "total_reviews": 2,
    "reviews": [
      {
        "review_id": 563240059,
        "rating": 5,
        "headline": "Love the feel of this toner.",
        "comments": "Love this toner.  It gave a nice glow and plumpness to my skin.   Am definitely going to buy again.",
        "nickname": "Anjali",
        "location": "Plano, tx",
        "created_date": 1757644615464,
        "bottom_line": "Yes",
        "helpful_votes": 0,
        "not_helpful_votes": 1
      },
      {
        "review_id": 562954648,
        "rating": 5,
        "headline": "I would buy this product again",
        "comments": "Love medicube. You need to get more of their products.",
        "nickname": "Denise",
        "location": "Delaware",
        "created_date": 1757269687917,
        "bottom_line": "Yes",
        "helpful_votes": 0,
        "not_helpful_votes": 3
      }
    ],
    "paging": {
      "total_results": 2,
      "pages_total": 1,
      "page_size": 20,
      "current_page_number": 1
    },
    "rollup": {
      "properties": [],
      "rating_histogram": [
        0,
        0,
        0,
        0,
        2
      ],
      "review_histogram": [
        0,
        0,
        0,
        0,
        2
      ],
      "rating_count": 2,
      "review_count": 2,
      "average_rating": 5.0,
      "recommended_ratio": 1.0,
      "media": [],
      "name": "PDRN Pink Niacinamide Milky Toner",
      "native_review_count": 2,
      "native_sampling_review_count": 0,
      "native_sweepstakes_review_count": 0,
      "native_community_content_review_count": 0,
      "syndicated_review_count": 0,
      "locale": "en_US"
    }
  }
}