{
  "product_id": "pimprod2053718",
  "product_url": "https://www.ulta.com/p/smoothing-lotion-pimprod2053718",
  "extracted_at": "2025-09-23T05:12:30.254227+00:00",
  "product_name": "MoroccanoilSmoothing Lotion",
  "brand": "Moroccanoil",
  "categories": [
    "Home",
    "Hair",
    "Styling Products",
    "Smoothing"
  ],
  "category_keys": [
    "home",
    "hair",
    "styling-products",
    "smoothing"
  ],
  "currency": "USD",
  "list_price": "",
  "sale_price": "36.00",
  "availability": "in_stock",
  "rating_avg": "",
  "rating_count": "",
  "images": [
    "https://media.ulta.com/i/ulta/2644272?w=500&h=500"
  ],
  "detailed_images": [
    "https://media.ulta.com/i/ulta/2644272?w=600&h=600&fmt=auto",
    "https://media.ulta.com/i/ulta/2644272_alt01?w=600&h=600&fmt=auto",
    "https://media.ulta.com/i/ulta/2644272_alt02?w=600&h=600&fmt=auto",
    "https://media.ulta.com/i/ulta/2644272_alt03?w=600&h=600&fmt=auto",
    "https://media.ulta.com/i/ulta/2644272_alt04?w=600&h=600&fmt=auto",
    "https://media.ulta.com/i/ulta/2644272_alt05?w=600&h=600&fmt=auto",
    "https://media.ulta.com/i/ulta/2644272_alt06?w=600&h=600&fmt=auto"
  ],
  "summary": "SummaryHighlightsClean IngredientsCruelty FreeVeganSustainable PackagingGive BackMoroccanoil Smoothing Lotion is a nourishing styling cream that controls frizz, increases manageability, and provides flexible hold.",
  "details": "DetailsBenefitsInstantly smooths frizz and flyawaysConditions and nourishes dry hairIncreases manageabilityProvides flexible hold and all-day definitionBottle made of 100% post-consumer recycled materialResearch ResultsLeaves hair 58% smoother*Reduces breakage by 72%**Results based*Based on an independent lab studyKey IngredientsArgan Oil: Antioxidant-rich natural oil that nourishArgan Butter: Natural conditioning agent that leaves hair soft, nourished, and shinyTiliaTomentosa Bud Extract: A hair conditioning agent derived from the buds of the Silver Linden TreeItem 2644272How To UseApply a small amount to damp hair. Style as desired. Use as a leave-in, next-day refresher.Caution: Use product only as directed. Avoid contact with eyes. In case of contact, rinse immediately with water. For external use only. Store at room temperature.IngredientsAqua/Water/Eau, Cetearyl Alcohol, Dimethicone, Glycerin, C13-15 Alkane, Hydrogenated Ethylhexyl Olivate, Parfum/Fragrance, Behentrimonium Chloride, Polyquaternium-70, C9-12 Alkane, Steareth-2, Argania Spinosa (Argan) Kernel Oil, Helianthus Annuus (Sunflower) Extract, Hydrogenated Olive Oil Unsaponifiables, Hydrogenated Vegetable Oil, Mauritia Flexuosa Fruit Oil, Oryza Sativa (Rice) Bran Extract, Rosmarinus Officinalis (Rosemary) Leaf Extract, Tilia Tomentosa Bud Extract, C11-13 Isoalkane, Oleth-10, Polyquaternium-37, Ppg-1 Trideceth-6, Tocopherol, Citric Acid, Caprylyl Glycol, Dipropylene Glycol, Glyceryl Stearate, Guar Hydroxypropyltrimonium Chloride, Heptyl Undecylenate, Propylene Glycol Dicaprylate/Dicaprate, Isopropyl Alcohol, Chlorphenesin, Phenoxyethanol, Potassium Hydroxide, Potassium Sorbate, Sodium Benzoate, Alpha-Isomethyl Ionone, Camphor, Carvone, Eucalyptus Globulus Oil, Hexamethylindanopyran, Lavandula (Lavender) Oil/Extract, Linalool, Linalyl Acetate, Mentha Viridis Leaf Oil, Pinene, Isoeugenyl Acetate, Tetramethyl Acetyloctahydronaphthalenes, Vanillin. MOSL06",
  "how_to_use": "Apply a small amount to damp hair. Style as desired. Use as a leave-in, next-day refresher.Caution: Use product only as directed. Avoid contact with eyes. In case of contact, rinse immediately with water. For external use only. Store at room temperature.",
  "ingredients": [
    "Aqua/Water/Eau",
    "Cetearyl Alcohol",
    "Dimethicone",
    "Glycerin",
    "C13-15 Alkane",
    "Hydrogenated Ethylhexyl Olivate",
    "Parfum/Fragrance",
    "Behentrimonium Chloride",
    "Polyquaternium-70",
    "C9-12 Alkane",
    "Steareth-2",
    "Argania Spinosa (Argan) Kernel Oil",
    "Helianthus Annuus (Sunflower) Extract",
    "Hydrogenated Olive Oil Unsaponifiables",
    "Hydrogenated Vegetable Oil",
    "Mauritia Flexuosa Fruit Oil",
    "Oryza Sativa (Rice) Bran Extract",
    "Rosmarinus Officinalis (Rosemary) Leaf Extract",
    "Tilia Tomentosa Bud Extract",
    "C11-13 Isoalkane",
    "Oleth-10",
    "Polyquaternium-37",
    "Ppg-1 Trideceth-6",
    "Tocopherol",
    "Citric Acid",
    "Caprylyl Glycol",
    "Dipropylene Glycol",
    "Glyceryl Stearate",
    "Guar Hydroxypropyltrimonium Chloride",
    "Heptyl Undecylenate",
    "Propylene Glycol Dicaprylate/Dicaprate",
    "Isopropyl Alcohol",
    "Chlorphenesin",
    "Phenoxyethanol",
    "Potassium Hydroxide",
    "Potassium Sorbate",
    "Sodium Benzoate",
    "Alpha-Isomethyl Ionone",
    "Camphor",
    "Carvone",
    "Eucalyptus Globulus Oil",
    "Hexamethylindanopyran",
    "Lavandula (Lavender) Oil/Extract",
    "Linalool",
    "Linalyl Acetate",
    "Mentha Viridis Leaf Oil",
    "Pinene",
    "Isoeugenyl Acetate",
    "Tetramethyl Acetyloctahydronaphthalenes",
    "Vanillin. MOSL06"
  ],
  "extended_contents": {},
  "tags": {
    "category": [
      "hair",
      "haircare"
    ],
    "product_type": [
      "moisturizer",
      "oil"
    ],
    "skin_type": [
      "dry"
    ],
    "finish": [
      "glossy",
      "sheer",
      "creamy",
      "cream",
      "oil"
    ],
    "ingredients": [
      "fragrance"
    ],
    "brand": [
      "mid-range",
      "mid-range"
    ],
    "special_features": [
      "cruelty-free",
      "vegan",
      "natural",
      "hydrating"
    ]
  },
  "reviews": {
    "product_id": "pimprod2053718",
    "total_reviews": 0,
    "reviews": [],
    "paging": {
      "total_results": 0,
      "pages_total": 0,
      "page_size": 20,
      "current_page_number": 1
    },
    "rollup": {}
  }
}