{
  "product_id": "pimprod2053247",
  "product_url": "https://www.ulta.com/p/retinol-01-caffeine-revitalizing-eye-cream-pimprod2053247",
  "extracted_at": "2025-09-23T05:02:05.007466+00:00",
  "product_name": "ANUARetinol 0.1 Caffeine Revitalizing Eye Cream",
  "brand": "ANUA",
  "categories": [
    "Home",
    "Skin Care",
    "Eye Treatments",
    "Eye Cream"
  ],
  "category_keys": [
    "home",
    "skin-care",
    "eye-treatments",
    "eye-cream"
  ],
  "currency": "USD",
  "list_price": "",
  "sale_price": "22.00",
  "availability": "in_stock",
  "rating_avg": "",
  "rating_count": "",
  "images": [
    "https://media.ulta.com/i/ulta/2646982?w=500&h=500"
  ],
  "detailed_images": [
    "https://media.ulta.com/i/ulta/2646982?w=600&h=600&fmt=auto",
    "https://media.ulta.com/i/ulta/2646982_alt01?w=600&h=600&fmt=auto",
    "https://media.ulta.com/i/ulta/2646982_alt02?w=600&h=600&fmt=auto",
    "https://media.ulta.com/i/ulta/2646982_alt03?w=600&h=600&fmt=auto",
    "https://media.ulta.com/i/ulta/2646982_alt04?w=600&h=600&fmt=auto",
    "https://media.ulta.com/i/ulta/2646982_alt05?w=600&h=600&fmt=auto",
    "https://media.ulta.com/i/ulta/2646982_alt06?w=600&h=600&fmt=auto",
    "https://media.ulta.com/i/ulta/2646982_alt07?w=600&h=600&fmt=auto"
  ],
  "summary": "SummaryHighlightsClean IngredientsSustainable PackagingAnua Retinol 0.1 Caffeine Revitalizing Eye Cream helps skin appear more radiant and balanced by addressing smile lines and eye area shading. It helps smooth skin texture for a youthful, refreshed look around the eyes.",
  "details": "DetailsBenefitsFormulated with 0.1% retinol and caffeine, this targeted eye cream is designed to care for under-eye shadows and sagging.Helps revitalize the skinâ€™s appearance and provides multi-benefit care for more luminous complexion.A fast-absorbing gentle & effective formula with 4 peptides and collagen helps skin look firmer, refreshed & revitalized.Infused with ceramides and hyaluronic acids, this lightweight eye cream deeply hydrates, and helps you say goodbye to a sleepless look.Key IngredientsRetinol 0.1% : Helps make the skin look firmer and youthful-looking.Caffeine 1% & Niacinamide 5% : Imporve your under-eye contours to achieve a natural glow.Ceramides & Hyaluronic Acid : Provide deep hydration with a moisture barrier.Research Results4.08% decrease in dark circle grade after 8 weeks1.63% increase in skin brighteness after 8 weeks13.49% decrease in fine lines after 8 weeks100% said skin around the eyes seems to be moist after 2 weeks of use100% said elasticity of skin around eyes seem to be improved after 2 weeks of use100% said morning swelling around the eyes seem to be improved after 2 weeks of useItem 2646982How To UseAfter cleansing, gently apply small dots around the eye area.If you're new to retinol, start by using it every other day and perform a patch test prior to use.IngredientsWater, Propanediol, Dipropylene Glycol, Niacinamide, Glycerin, Limnanthes Alba (Meadowfoam) Seed Oil, Pentylene Glycol, Cyclohexasiloxane, Polyglyceryl-3 Methylglucose Distearate, Polyglyceryl-3 Distearate, 1,2-Hexanediol, Caffeine, Panthenol, Soluble Collagen, Squalane, Adenosine, Ceramide NP, Ceramide NG, Ceramide NS, Ceramide AP, Ceramide AS, Ceramide EOP, Hexapeptide-2, Copper Tripeptide-1, Acetyl Hexapeptide-8, Acetyl Dipeptide-1 Cetyl Ester, Retinol, Hydrolyzed Hyaluronic Acid, Hyaluronic Acid, Sodium Hyaluronate, Sodium Hyaluronate Crosspolymer, Dimethylsilanol Hyaluronate, Hydrolyzed Sodium Hyaluronate, Potassium Hyaluronate, Hydroxypropyltrimonium Hyaluronate, Sodium Hyaluronate Dimethylsilanol, Sodium Acetylated Hyaluronate, Hippophae Rhamnoides Oil, Macadamia Ternifolia Seed Oil, Chitosan, Butyrospermum Parkii (Shea) Butter, Hippophae Rhamnoides Fruit Oil, Pentaerythrityl Tetraethylhexanoate, Hydroxyethyl Acrylate/Sodium Acryloyldimethyl Taurate Copolymer, Diglycerin, Polymethylsilsesquioxane, Tocopheryl Acetate, Sodium Polyacryloyldimethyl Taurate, Hydrogenated Polydecene, Hydroxyacetophenone, Glyceryl Stearate Citrate, Caprylic/Capric Triglyceride, Sodium Phytate, Butylene Glycol, Trideceth-10, Hydrogenated Lecithin, Sorbitan Isostearate, Palmitic Acid, Stearic Acid, Brassica Campestris (Rapeseed) Sterols, Cholesterol, Polyglyceryl-10 Laurate, Phytosteryl/Behenyl/Octyldodecyl Lauroyl Glutamate, Aluminum/Magnesium Hydroxide Stearate, Pentaerythrityl Tetra-di-t-butyl Hydroxyhydrocinnamate, Oleic Acid, Potassium Cetyl Phosphate, Tris(Tetramethylhydroxypiperidinol) Citrate, Octyldodecanol, Phytosterols, Sorbitan Laurate, Hydroxyethylcellulose, Phytosphingosine, Biotin, Cetearyl Alcohol, Xanthan Gum.",
  "how_to_use": "After cleansing, gently apply small dots around the eye area.If you're new to retinol, start by using it every other day and perform a patch test prior to use.",
  "ingredients": [
    "Water",
    "Propanediol",
    "Dipropylene Glycol",
    "Niacinamide",
    "Glycerin",
    "Limnanthes Alba (Meadowfoam) Seed Oil",
    "Pentylene Glycol",
    "Cyclohexasiloxane",
    "Polyglyceryl-3 Methylglucose Distearate",
    "Polyglyceryl-3 Distearate",
    "2-Hexanediol",
    "Caffeine",
    "Panthenol",
    "Soluble Collagen",
    "Squalane",
    "Adenosine",
    "Ceramide NP",
    "Ceramide NG",
    "Ceramide NS",
    "Ceramide AP",
    "Ceramide AS",
    "Ceramide EOP",
    "Hexapeptide-2",
    "Copper Tripeptide-1",
    "Acetyl Hexapeptide-8",
    "Acetyl Dipeptide-1 Cetyl Ester",
    "Retinol",
    "Hydrolyzed Hyaluronic Acid",
    "Hyaluronic Acid",
    "Sodium Hyaluronate",
    "Sodium Hyaluronate Crosspolymer",
    "Dimethylsilanol Hyaluronate",
    "Hydrolyzed Sodium Hyaluronate",
    "Potassium Hyaluronate",
    "Hydroxypropyltrimonium Hyaluronate",
    "Sodium Hyaluronate Dimethylsilanol",
    "Sodium Acetylated Hyaluronate",
    "Hippophae Rhamnoides Oil",
    "Macadamia Ternifolia Seed Oil",
    "Chitosan",
    "Butyrospermum Parkii (Shea) Butter",
    "Hippophae Rhamnoides Fruit Oil",
    "Pentaerythrityl Tetraethylhexanoate",
    "Hydroxyethyl Acrylate/Sodium Acryloyldimethyl Taurate Copolymer",
    "Diglycerin",
    "Polymethylsilsesquioxane",
    "Tocopheryl Acetate",
    "Sodium Polyacryloyldimethyl Taurate",
    "Hydrogenated Polydecene",
    "Hydroxyacetophenone",
    "Glyceryl Stearate Citrate",
    "Caprylic/Capric Triglyceride",
    "Sodium Phytate",
    "Butylene Glycol",
    "Trideceth-10",
    "Hydrogenated Lecithin",
    "Sorbitan Isostearate",
    "Palmitic Acid",
    "Stearic Acid",
    "Brassica Campestris (Rapeseed) Sterols",
    "Cholesterol",
    "Polyglyceryl-10 Laurate",
    "Phytosteryl/Behenyl/Octyldodecyl Lauroyl Glutamate",
    "Aluminum/Magnesium Hydroxide Stearate",
    "Pentaerythrityl Tetra-di-t-butyl Hydroxyhydrocinnamate",
    "Oleic Acid",
    "Potassium Cetyl Phosphate",
    "Tris(Tetramethylhydroxypiperidinol) Citrate",
    "Octyldodecanol",
    "Phytosterols",
    "Sorbitan Laurate",
    "Hydroxyethylcellulose",
    "Phytosphingosine",
    "Biotin",
    "Cetearyl Alcohol",
    "Xanthan Gum"
  ],
  "extended_contents": {},
  "tags": {
    "category": [
      "eye",
      "eyes"
    ],
    "product_type": [
      "moisturizer",
      "mask",
      "treatment",
      "eye cream"
    ],
    "skin_type": [
      "sensitive",
      "normal"
    ],
    "finish": [
      "dewy",
      "sheer",
      "creamy",
      "cream",
      "oil",
      "foam"
    ],
    "ingredients": [
      "hyaluronic-acid",
      "retinol",
      "niacinamide",
      "peptides",
      "ceramides",
      "collagen"
    ],
    "brand": [
      "mid-range",
      "affordable"
    ],
    "special_features": [
      "natural",
      "brightening",
      "soothing",
      "purifying"
    ]
  },
  "reviews": {
    "product_id": "pimprod2053247",
    "total_reviews": 0,
    "reviews": [],
    "paging": {
      "total_results": 0,
      "pages_total": 0,
      "page_size": 20,
      "current_page_number": 1
    },
    "rollup": {}
  }
}