{
  "product_id": "pimprod2053914",
  "product_url": "https://www.ulta.com/p/connect-pore-4-piece-skincare-gift-set-pimprod2053914",
  "extracted_at": "2025-09-23T03:40:24.120924+00:00",
  "product_name": "Benefit CosmeticsConnect Pore 4-Piece Skincare Gift Set",
  "brand": "Benefit Cosmetics",
  "categories": [
    "Home",
    "Skin Care",
    "Treatment & Serums",
    "Face Masks"
  ],
  "category_keys": [
    "home",
    "skin-care",
    "men",
    "face"
  ],
  "currency": "USD",
  "list_price": "",
  "sale_price": "42.00",
  "availability": "in_stock",
  "rating_avg": "",
  "rating_count": "",
  "images": [
    "https://media.ulta.com/i/ulta/2643574?w=500&h=500"
  ],
  "detailed_images": [
    "https://media.ulta.com/i/ulta/2643574?w=600&h=600&fmt=auto",
    "https://media.ulta.com/i/ulta/2643574_sm?w=600&h=600&fmt=auto",
    "https://media.ulta.com/i/ulta/2643574_alt01?w=600&h=600&fmt=auto",
    "https://media.ulta.com/i/ulta/2643574_alt02?w=600&h=600&fmt=auto",
    "https://media.ulta.com/i/ulta/2643574_alt03?w=600&h=600&fmt=auto",
    "https://media.ulta.com/i/ulta/2643574_alt04?w=600&h=600&fmt=auto",
    "https://media.ulta.com/i/ulta/2643574_alt05?w=600&h=600&fmt=auto",
    "https://media.ulta.com/i/ulta/2643574_alt06?w=600&h=600&fmt=auto",
    "https://media.ulta.com/i/ulta/2643574_alt07?w=600&h=600&fmt=auto",
    "https://media.ulta.com/v/ulta/2643574_vid01/thumbs/05176cfa-d151-468b-aa46-f0d645260a7c?w=600&h=1071&fmt=auto",
    "https://media.ulta.com/v/ulta/2643574_vid02/thumbs/cd63b8bd-b254-4eca-8c90-1e5b1b7ce75a?w=600&h=337&fmt=auto"
  ],
  "summary": "SummaryHighlightsSustainable PackagingIt's time to make winning moves and unblock pores with Benefit Connect Pore 4-Piece Skincare Gift Set. The POREfessional Get Unblocked cleansing oil to melt away makeup & The POREfessional Deep Retreat clay mask for a mattifying deep clean. Instant hydration with The POREfessional Smooth Sip.",
  "details": "DetailsIncludesThe POREfessional Get Unblocked pore-clearing makeup-removing cleansing oil miniThe POREfessional Deep Retreat pore-clearing clay mask miniThe POREfessional Smooth Sip lightweight smoothing moisturizer for pores miniKeepsake Beauty BagItem 2643574How To UseApply The POREfessional Get Unblocked with dry hands. Massage thoroughly in circular motions.Wet hands and keep massaging to emulsify. Rinse fully.Apply The POREfessional Deep Retreat to clean, dry face & neck weekly. Leave on for 30 minutes or until dry. Rinse.Apply The POREfessional Smooth Sip to clean face & neck. Use daily AM & PMIngredientsAqua (Water), Kaolin, Silica, Glycerin, Butylene Glycol, Pentylene Glycol, CI 77007 (Ultramarines), Peg-40 Sorbitan Peroleate, Sodium Acrylates Copolymer, Caprylic/Capric Triglyceride, CI 77499 (Iron Oxides), Hydroxyacetophenone, Lecithin, Mica, Chlorphenesin, Bisabolol, CI 77491 (Iron Oxides), Hydrogenated Vegetable Oil, Opuntia Coccinellifera Flower Extract, CI 77891 (Titanium Dioxide), Trisodium Ethylenediamine Disuccinate, Simmondsia Chinensis (Jojoba) Seed Oil, Prunus Domestica Seed Oil, Parfum (Fragrance), Disodium Phosphate, Potassium Hydroxide, Xanthan Gum, Crithmum Maritimum Extract, 1,2-Hexanediol, Caprylyl Glycol, Tocopherol, CI 77510 (Ferric Ferrocyanide), Sodium Phosphate, Sphingolipids, Sphingomonas Ferment Extract, Tocopheryl Acetate, Citric Acid, Pentaerythrityl Tetra-Di-T-Butyl Hydroxyhydrocinnamate, Sodium Citrate. N° 16588Caprylic/Capric Triglyceride, Simmondsia Chinensis (Jojoba) Seed Oil, Peg-40 Sorbitan Peroleate, Persea Gratissima (Avocado) Oil, Vitis Vinifera (Grape) Seed Oil, 1,2-Hexanediol, Caprylyl Glycol, Parfum (Fragrance), Bisabolol, Prunus Domestica Seed Oil, Triethyl Citrate, Tocopherol, Ceramide Np, Tocopheryl Acetate, Pentaerythrityl Tetra-Di-T-Butyl Hydroxyhydrocinnamate. N° 17004Aqua (Water), Propanediol, Glycerin, Niacinamide, Caprylic/Capric Triglyceride, Cellulose, Squalane, Maltitol, Ammonium Acryloyldimethyltaurate/Vp Copolymer, Acrylates/C10-30 Alkyl Acrylate Crosspolymer, Chlorphenesin, Hydroxyacetophenone, Bisabolol, Xanthan Gum, Parfum (Fragrance), Aloe Barbadensis Leaf Juice, Sodium Hydroxide, Sclerotium Gum, Sorbitan Trioleate, Hydrogenated Lecithin, Pullulan, Butylene Glycol, Pentylene Glycol, Phenethyl Alcohol, Saccharide Isomerate, Silica, Apium Graveolens (Celery) Seed Extract, Sphingolipids, Sphingomonas Ferment Extract, Linum Usitatissimum (Linseed) Seed Extract, Citric Acid, Pentaerythrityl Tetra-Di-T-Butyl Hydroxyhydrocinnamate, Sodium Citrate, Tocopherol. N° 16589Disclaimer: Product Ingredient Listings Are Updated Periodically. Before Using A Benefit Product, Please Read The Ingredient List On The Packaging Of Your Product To Be Sure That The Ingredients Are Appropriate For Your Personal Use.",
  "how_to_use": "Apply The POREfessional Get Unblocked with dry hands. Massage thoroughly in circular motions.Wet hands and keep massaging to emulsify. Rinse fully.Apply The POREfessional Deep Retreat to clean, dry face & neck weekly. Leave on for 30 minutes or until dry. Rinse.Apply The POREfessional Smooth Sip to clean face & neck. Use daily AM & PM",
  "ingredients": [
    "Aqua (Water)",
    "Kaolin",
    "Silica",
    "Glycerin",
    "Butylene Glycol",
    "Pentylene Glycol",
    "Peg-40 Sorbitan Peroleate",
    "Sodium Acrylates Copolymer",
    "Caprylic/Capric Triglyceride",
    "Hydroxyacetophenone",
    "Lecithin",
    "Mica",
    "Chlorphenesin",
    "Bisabolol",
    "Hydrogenated Vegetable Oil",
    "Opuntia Coccinellifera Flower Extract",
    "Trisodium Ethylenediamine Disuccinate",
    "Simmondsia Chinensis (Jojoba) Seed Oil",
    "Prunus Domestica Seed Oil",
    "Parfum (Fragrance)",
    "Disodium Phosphate",
    "Potassium Hydroxide",
    "Xanthan Gum",
    "Crithmum Maritimum Extract",
    "2-Hexanediol",
    "Caprylyl Glycol",
    "Tocopherol",
    "Sodium Phosphate",
    "Sphingolipids",
    "Sphingomonas Ferment Extract",
    "Tocopheryl Acetate",
    "Citric Acid",
    "Pentaerythrityl Tetra-Di-T-Butyl Hydroxyhydrocinnamate",
    "Sodium Citrate. N° 16588Caprylic/Capric Triglyceride",
    "Simmondsia Chinensis (Jojoba) Seed Oil",
    "Peg-40 Sorbitan Peroleate",
    "Persea Gratissima (Avocado) Oil",
    "Vitis Vinifera (Grape) Seed Oil",
    "2-Hexanediol",
    "Caprylyl Glycol",
    "Parfum (Fragrance)",
    "Bisabolol",
    "Prunus Domestica Seed Oil",
    "Triethyl Citrate",
    "Tocopherol",
    "Ceramide Np",
    "Tocopheryl Acetate",
    "Pentaerythrityl Tetra-Di-T-Butyl Hydroxyhydrocinnamate. N° 17004Aqua (Water)",
    "Propanediol",
    "Glycerin",
    "Niacinamide",
    "Caprylic/Capric Triglyceride",
    "Cellulose",
    "Squalane",
    "Maltitol",
    "Ammonium Acryloyldimethyltaurate/Vp Copolymer",
    "Acrylates/C10-30 Alkyl Acrylate Crosspolymer",
    "Chlorphenesin",
    "Hydroxyacetophenone",
    "Bisabolol",
    "Xanthan Gum",
    "Parfum (Fragrance)",
    "Aloe Barbadensis Leaf Juice",
    "Sodium Hydroxide",
    "Sclerotium Gum",
    "Sorbitan Trioleate",
    "Hydrogenated Lecithin",
    "Pullulan",
    "Butylene Glycol",
    "Pentylene Glycol",
    "Phenethyl Alcohol",
    "Saccharide Isomerate",
    "Silica",
    "Apium Graveolens (Celery) Seed Extract",
    "Sphingolipids",
    "Sphingomonas Ferment Extract",
    "Linum Usitatissimum (Linseed) Seed Extract",
    "Citric Acid",
    "Pentaerythrityl Tetra-Di-T-Butyl Hydroxyhydrocinnamate",
    "Sodium Citrate",
    "Tocopherol. N° 16589Disclaimer: Product Ingredient Listings Are Updated Periodically. Before Using A Benefit Product",
    "Please Read The Ingredient List On The Packaging Of Your Product To Be Sure That The Ingredients Are Appropriate For Your Personal Use"
  ],
  "extended_contents": {},
  "tags": {
    "category": [
      "men",
      "face",
      "mens"
    ],
    "product_type": [
      "serum",
      "mask",
      "treatment"
    ],
    "skin_type": [
      "dry"
    ],
    "finish": [
      "sheer",
      "creamy",
      "oil"
    ],
    "ingredients": [
      "niacinamide",
      "ceramides",
      "fragrance"
    ],
    "brand": [
      "mid-range",
      "mid-range"
    ],
    "special_features": [
      "purifying"
    ]
  },
  "reviews": {
    "product_id": "pimprod2053914",
    "total_reviews": 0,
    "reviews": [],
    "paging": {
      "total_results": 0,
      "pages_total": 0,
      "page_size": 20,
      "current_page_number": 1
    },
    "rollup": {}
  }
}