{
  "product_id": "pimprod2053799",
  "product_url": "https://www.ulta.com/p/shake-shine-day-2-refresh-pimprod2053799",
  "extracted_at": "2025-09-23T05:08:19.147708+00:00",
  "product_name": "CurlsmithShake & Shine Day 2 Refresh",
  "brand": "Curlsmith",
  "categories": [
    "Home",
    "Hair",
    "Styling Products",
    "Curl Enhancing"
  ],
  "category_keys": [
    "home",
    "hair",
    "styling-products",
    "curl-enhancing"
  ],
  "currency": "USD",
  "list_price": "",
  "sale_price": "29.00",
  "availability": "in_stock",
  "rating_avg": "",
  "rating_count": "",
  "images": [
    "https://media.ulta.com/i/ulta/2643516?w=500&h=500"
  ],
  "detailed_images": [
    "https://media.ulta.com/i/ulta/2643516?w=600&h=600&fmt=auto",
    "https://media.ulta.com/i/ulta/2643516_alt01?w=600&h=600&fmt=auto",
    "https://media.ulta.com/i/ulta/2643516_alt02?w=600&h=600&fmt=auto",
    "https://media.ulta.com/i/ulta/2643516_alt03?w=600&h=600&fmt=auto",
    "https://media.ulta.com/i/ulta/2643516_alt04?w=600&h=600&fmt=auto",
    "https://media.ulta.com/i/ulta/2643516_alt05?w=600&h=600&fmt=auto",
    "https://media.ulta.com/i/ulta/2643516_alt06?w=600&h=600&fmt=auto",
    "https://media.ulta.com/v/ulta/2643516_vid01/thumbs/7646cd67-8391-4b2a-b6d7-b665f2919589?w=600&h=337&fmt=auto"
  ],
  "summary": "SummaryHighlightsCruelty FreeSustainable PackagingGive BackIntroducing Curlsmith's revolutionary bi-phase Curl Refreshing Mist, an innovative solution crafted specifically for curly hair. Ideal to extend the result of a wash day.",
  "details": "DetailsBenefitsA curl refreshing mist to refresh, moisturize and define. Designed to refresh curls in between wash days.Up to 41% increase in hydration*Delivers long-lasting frizz control - for up to 24 hours*Reduces frizz by up to 71%*Contains 7 types of Hyaluronic Acids. Known to help maintain balanced hydration & enhance smoothness*Based on third party testing vs controlFeaturesWHO IS IT FOR? All curl types & textures.BEST FOR: Best for wavy and curly hair.FORMAT: Light mistRECOMMENDED FREQUENCY: Regular useColor-SafeMade without sulphates, silicones or drying alcoholsItem 2643516How To UseShake well. Spray and mist sparingly through dry hair to reactivate curls. Ensure all strands are evenly coated and redefine your curls. Leave to air dry.IngredientsWater (Aqua/Eau), Caprylic/Capric Triglyceride, Propanediol, C13-15 Alkane, Squalane, Glycerin, Xylitylglucoside, Octyldodecanol, Vaccinium Macrocarpon (Cranberry) Seed Oil, Prunus Armeniaca (Apricot) Kernel Oil, Persea Gratissima (Avocado) Oil, Carapa Guaianensis Seed Oil, Hippophae Rhamnoides Fruit Oil, Diethylhexyl Syringylidenemalonate, Sodium Hyaluronate, Pisum Sativum (Pea) Seed Extract, Musa Sapientum (Banana) Fruit Extract, Aloe Barbadensis Leaf Juice, Pelvetia Canaliculata Extract, Olea Europaea (Olive) Fruit Oil , Salvia Officinalis (Sage) Leaf Extract, Rosmarinus Officinalis (Rosemary) Leaf Extract, Piper Nigrum (Pepper) Seed Extract, Ocimum Basilicum (Basil) Leaf Extract, Anhydroxylitol, Maltitol, Selaginella Lepidophylla Extract, Haematococcus Pluvialis Extract, Heptyl Glucoside, Panthenol, Hydrolyzed Quinoa, Tocopheryl Acetate, Lactic Acid, 1,2-Hexanediol, Benzyl Alcohol, Sodium Chloride, Xylitol, Tetrasodium Glutamate Diacetate, Citric Acid, Ethylhexylglycerin, Sorbic Acid, Tocopherol, Sodium Benzoate, Potassium Sorbate, Phenoxyethanol, Fragrance (Parfum), Limonene, Linalool, Citrus Limon (Lemon) Peel Oil, Pinene, Tetramethyl Acetyloctahydronaphthalenes.",
  "how_to_use": "Shake well. Spray and mist sparingly through dry hair to reactivate curls. Ensure all strands are evenly coated and redefine your curls. Leave to air dry.",
  "ingredients": [
    "Water (Aqua/Eau)",
    "Caprylic/Capric Triglyceride",
    "Propanediol",
    "C13-15 Alkane",
    "Squalane",
    "Glycerin",
    "Xylitylglucoside",
    "Octyldodecanol",
    "Vaccinium Macrocarpon (Cranberry) Seed Oil",
    "Prunus Armeniaca (Apricot) Kernel Oil",
    "Persea Gratissima (Avocado) Oil",
    "Carapa Guaianensis Seed Oil",
    "Hippophae Rhamnoides Fruit Oil",
    "Diethylhexyl Syringylidenemalonate",
    "Sodium Hyaluronate",
    "Pisum Sativum (Pea) Seed Extract",
    "Musa Sapientum (Banana) Fruit Extract",
    "Aloe Barbadensis Leaf Juice",
    "Pelvetia Canaliculata Extract",
    "Olea Europaea (Olive) Fruit Oil",
    "Salvia Officinalis (Sage) Leaf Extract",
    "Rosmarinus Officinalis (Rosemary) Leaf Extract",
    "Piper Nigrum (Pepper) Seed Extract",
    "Ocimum Basilicum (Basil) Leaf Extract",
    "Anhydroxylitol",
    "Maltitol",
    "Selaginella Lepidophylla Extract",
    "Haematococcus Pluvialis Extract",
    "Heptyl Glucoside",
    "Panthenol",
    "Hydrolyzed Quinoa",
    "Tocopheryl Acetate",
    "Lactic Acid",
    "2-Hexanediol",
    "Benzyl Alcohol",
    "Sodium Chloride",
    "Xylitol",
    "Tetrasodium Glutamate Diacetate",
    "Citric Acid",
    "Ethylhexylglycerin",
    "Sorbic Acid",
    "Tocopherol",
    "Sodium Benzoate",
    "Potassium Sorbate",
    "Phenoxyethanol",
    "Fragrance (Parfum)",
    "Limonene",
    "Linalool",
    "Citrus Limon (Lemon) Peel Oil",
    "Pinene",
    "Tetramethyl Acetyloctahydronaphthalenes"
  ],
  "extended_contents": {},
  "tags": {
    "category": [
      "hair",
      "haircare"
    ],
    "product_type": [
      "day cream"
    ],
    "skin_type": [
      "dry",
      "normal"
    ],
    "finish": [
      "sheer",
      "long-wear",
      "creamy",
      "oil"
    ],
    "ingredients": [
      "lactic-acid",
      "fragrance"
    ],
    "brand": [
      "mid-range",
      "mid-range"
    ],
    "special_features": [
      "cruelty-free"
    ]
  },
  "reviews": {
    "product_id": "pimprod2053799",
    "total_reviews": 0,
    "reviews": [],
    "paging": {
      "total_results": 0,
      "pages_total": 0,
      "page_size": 20,
      "current_page_number": 1
    },
    "rollup": {}
  }
}