{
  "product_id": "pimprod2053800",
  "product_url": "https://www.ulta.com/p/frizz-rescue-curl-retainer-pimprod2053800",
  "extracted_at": "2025-09-23T03:56:49.148891+00:00",
  "product_name": "CurlsmithFrizz Rescue Curl Retainer",
  "brand": "Curlsmith",
  "categories": [
    "Home",
    "Hair",
    "Styling Products",
    "Curl Enhancing"
  ],
  "category_keys": [
    "home",
    "hair",
    "styling-products",
    "curl-enhancing"
  ],
  "currency": "USD",
  "list_price": "",
  "sale_price": "28.00",
  "availability": "in_stock",
  "rating_avg": "",
  "rating_count": "",
  "images": [
    "https://media.ulta.com/i/ulta/2643544?w=500&h=500"
  ],
  "detailed_images": [
    "https://media.ulta.com/i/ulta/2643544?w=600&h=600&fmt=auto",
    "https://media.ulta.com/i/ulta/2643544_alt01?w=600&h=600&fmt=auto",
    "https://media.ulta.com/i/ulta/2643544_alt02?w=600&h=600&fmt=auto",
    "https://media.ulta.com/i/ulta/2643544_alt03?w=600&h=600&fmt=auto",
    "https://media.ulta.com/i/ulta/2643544_alt04?w=600&h=600&fmt=auto",
    "https://media.ulta.com/i/ulta/2643544_alt05?w=600&h=600&fmt=auto",
    "https://media.ulta.com/i/ulta/2643544_alt06?w=600&h=600&fmt=auto"
  ],
  "summary": "SummaryHighlightsCruelty FreeSustainable PackagingGive BackCurlsmith Frizz Rescue Curl Retainer is a jelly styler that provides exceptional frizz reduction and defines curls with medium hold-no stickiness or stiffness.",
  "details": "DetailsBenefitsA non-sticky jelly that retains curls and definition and will give soft, smooth and bouncy curls that last.Controls frizz up to 72hrs in extreme humidity*Reduces frizz by up to 79% for up to 72hrs*87% agreed their curls felt soft and bouncy**Made with a tri-oil blend that forms an invisible layer helping curls stay defined*Based on third party testing**Based on an independent study on people with wavy, curly, coily hairFeaturesBEST FOR: Frizzy hairFORMAT: JellyHOLD LEVEL: 6-Medium holdColor-SafeMade without sulphates, silicones or drying alcoholsItem 2643544How To UseApply to wet hair. Rake through to ensure you are evenly coating all strands. Style as desired and leave to air dry or diffuse.IngredientsWater (Aqua/Eau), Propanediol, Helianthus Annuus (Sunflower) Seed Extract, Hydrolyzed Corn Starch, Corn Starch Modified, Argania Spinosa (Argan) Kernel Oil, Citrullus Lanatus (Watermelon) Seed Oil, Ribes Nigrum (Black Currant) Seed Oil, Panthenol, Helianthus Annuus (Sunflower) Seed Oil, PVP, Cocos Nucifera (Coconut) Seed Butter, Niacinamide, Squalane, Glycerin, C9-12 Alkane, Coco-Caprylate/Caprate, Behentrimonium Chloride, Caesalpinia Spinosa Gum, Polyacrylate Crosspolymer-6, Tocopherol, Laureth-2, Pentylene Glycol, Sodium Gluconate, Sodium Hydroxide, Citric Acid, Ethylhexylglycerin, Phenoxyethanol, S odium Benzoate, Potassium Sorbate, Fragrance (Parfum), Limonene, Linalool, Citronellol, Alpha-Terpinene, Dimethyl Phenethyl Acetate, Tetramethyl Acetyloctahydronaphthalenes, Citrus Limon (Lemon) Peel Oil, Citrus Aurantium (Orange) Peel Oil, Pinene, Rose Ketones, Vanillin.",
  "how_to_use": "Apply to wet hair. Rake through to ensure you are evenly coating all strands. Style as desired and leave to air dry or diffuse.",
  "ingredients": [
    "Water (Aqua/Eau)",
    "Propanediol",
    "Helianthus Annuus (Sunflower) Seed Extract",
    "Hydrolyzed Corn Starch",
    "Corn Starch Modified",
    "Argania Spinosa (Argan) Kernel Oil",
    "Citrullus Lanatus (Watermelon) Seed Oil",
    "Ribes Nigrum (Black Currant) Seed Oil",
    "Panthenol",
    "Helianthus Annuus (Sunflower) Seed Oil",
    "PVP",
    "Cocos Nucifera (Coconut) Seed Butter",
    "Niacinamide",
    "Squalane",
    "Glycerin",
    "C9-12 Alkane",
    "Coco-Caprylate/Caprate",
    "Behentrimonium Chloride",
    "Caesalpinia Spinosa Gum",
    "Polyacrylate Crosspolymer-6",
    "Tocopherol",
    "Laureth-2",
    "Pentylene Glycol",
    "Sodium Gluconate",
    "Sodium Hydroxide",
    "Citric Acid",
    "Ethylhexylglycerin",
    "Phenoxyethanol",
    "S odium Benzoate",
    "Potassium Sorbate",
    "Fragrance (Parfum)",
    "Limonene",
    "Linalool",
    "Citronellol",
    "Alpha-Terpinene",
    "Dimethyl Phenethyl Acetate",
    "Tetramethyl Acetyloctahydronaphthalenes",
    "Citrus Limon (Lemon) Peel Oil",
    "Citrus Aurantium (Orange) Peel Oil",
    "Pinene",
    "Rose Ketones",
    "Vanillin"
  ],
  "extended_contents": {},
  "tags": {
    "category": [
      "hair",
      "haircare"
    ],
    "skin_type": [
      "oily",
      "dry"
    ],
    "finish": [
      "sheer",
      "creamy",
      "gel",
      "oil"
    ],
    "ingredients": [
      "niacinamide",
      "fragrance"
    ],
    "brand": [
      "mid-range",
      "mid-range"
    ],
    "special_features": [
      "cruelty-free"
    ],
    "product_type": []
  },
  "reviews": {
    "product_id": "pimprod2053800",
    "total_reviews": 0,
    "reviews": [],
    "paging": {
      "total_results": 0,
      "pages_total": 0,
      "page_size": 20,
      "current_page_number": 1
    },
    "rollup": {}
  }
}