{
  "product_id": "",
  "product_url": "https://www.ulta.com/p/acne-clearing-skin-wash-VP12691",
  "extracted_at": "2025-09-23T03:10:59.599308+00:00",
  "product_name": "DermalogicaAcne Clearing Skin Wash",
  "brand": "Dermalogica",
  "categories": [
    "Home",
    "Skin Care",
    "Treatment & Serums",
    "Acne & Blemish Treatments"
  ],
  "category_keys": [
    "home",
    "skin-care",
    "men",
    "men"
  ],
  "currency": "USD",
  "list_price": "",
  "sale_price": "48.00",
  "availability": "in_stock",
  "rating_avg": "4.5",
  "rating_count": "1331",
  "images": [
    "https://media.ulta.com/i/ulta/2547231?w=500&h=500"
  ],
  "detailed_images": [
    "https://media.ulta.com/i/ulta/2547231?w=600&h=600&fmt=auto",
    "https://media.ulta.com/i/ulta/2547231cm_alt01?w=600&h=600&fmt=auto",
    "https://media.ulta.com/i/ulta/2547231cm_alt02?w=600&h=600&fmt=auto",
    "https://media.ulta.com/i/ulta/2547231cm_alt03?w=600&h=600&fmt=auto",
    "https://media.ulta.com/i/ulta/2547231cm_alt04?w=600&h=600&fmt=auto",
    "https://media.ulta.com/i/ulta/2547231cm_alt05?w=600&h=600&fmt=auto",
    "https://media.ulta.com/i/ulta/2547231cm_alt06?w=600&h=600&fmt=auto",
    "https://media.ulta.com/i/ulta/2547231cm_alt07?w=600&h=600&fmt=auto",
    "https://media.ulta.com/v/ulta/2547231cm_vid01/thumbs/77ba5b59-3f5e-438e-9f6c-556487761534?w=600&h=337&fmt=auto"
  ],
  "summary": "SummaryHighlightsClean IngredientsCruelty FreeVeganSustainable PackagingGive BackDermalogica's Acne Clearing Skin Wash is a naturally-foaming cleanser, perfect for controlling breakouts and excess surface oils.",
  "details": "DetailsBenefitsNon-irritating, naturally-foaming cleanser that helps clear skin and reduce visible skin agingHelps to clear skinNatural exfoliation helps to clear clogged folliclesClears away excess oil without stripping skinPrevents future breakoutsGreat for \"Back-ne\" (acne on the back)Soothing botanicals help calm irritationBest for those concerned with large pores, acne blemishes, hormonal break outs, oily and acne-prone skinKey IngredientsSalicylic Acid (a Beta Hydroxy Acid): stimulates natural exfoliation to help clear clogged follicles and smooth away dullnessMenthol and Camphor: help calm inflammationContains natural extracts of Balm Mint, Eucalyptus and Tea TreeItem 2547231How To UseWork a pea-sized amount into a lather in wet hands. Apply to dampened face and neck, massaging in circular motions while concentrating on areas of congestion and oiliness. Avoid eye area. Rinse thoroughly with warm water.IngredientsWater/Aqua/Eau, Glycerin, Sodium Laurylglucosides Hydroxypropylsulfonate, Sodium Methyl Cocoyl Taurate, Cocamidopropyl Betaine, Hydroxypropyl Bis-Hydroxyethyldimonium Chloride, PEG-120 Methyl Glucose Dioleate, Butylene Glycol, Sodium PCA, Salicylic Acid, Phytic Acid, Butyrospermum Parkii (Shea) Butter, Fucus Vesiculosus Extract, Curcuma Longa (Turmeric) Root Extract, Aloe Barbadensis Flower Extract, Allium Sativum (Garlic) Bulb Extract, Laminaria Ochroleuca Extract, Passiflora Incarnata Extract, Salvia Officinalis (Sage) Leaf Extract, Camphor, Menthol, Eucalyptus Globulus Leaf Extract, Hamamelis Virginiana (Witch Hazel) Leaf Extract, Solanum Melongena (Eggplant) Fruit Extract, Cocamidopropyl Dimethylamine, Sodium Methyl Oleoyl Taurate, Dipotassium Glycyrrhizate, Tetrasodium Glutamate Diacetate, Polysorbate 80, Melaleuca Alternifolia (Tea Tree) Leaf Oil, Melia Azadirachta Leaf Extract, Melia Azadirachta Flower Extract, Corallina Officinalis Extract, Melissa Officinalis Flower/Leaf/Stem Extract, Coccinia Indica Fruit Extract, Angelica Archangelica Extract, Chamomilla Recutita (Matricaria) Flower Extract, Citrus Limon (Lemon) Fruit Extract, Echinacea Angustifolia Leaf Extract, Ethylhexylglycerin, Ocimum Basilicum (Basil) Flower/Leaf Extract, Ocimum Sanctum Leaf Extract, Anthemis Nobilis Flower Extract, Ascorbic Acid, Camellia Sinensis Leaf Extract, Maltodextrin, Silica, Palmitic Acid, Zinc PCA, Kaolin, Palmitoyl Tripeptide-5, Aminomethyl Propanol, Sodium Chloride, Sodium Hydroxide, Benzyl PCA, Phenoxyethanol.Shipping & Coupon RestrictionsThis brand is excluded from most Ulta Beauty coupons.See brand eligibility details",
  "how_to_use": "Work a pea-sized amount into a lather in wet hands. Apply to dampened face and neck, massaging in circular motions while concentrating on areas of congestion and oiliness. Avoid eye area. Rinse thoroughly with warm water.",
  "ingredients": [
    "Water/Aqua/Eau",
    "Glycerin",
    "Sodium Laurylglucosides Hydroxypropylsulfonate",
    "Sodium Methyl Cocoyl Taurate",
    "Cocamidopropyl Betaine",
    "Hydroxypropyl Bis-Hydroxyethyldimonium Chloride",
    "PEG-120 Methyl Glucose Dioleate",
    "Butylene Glycol",
    "Sodium PCA",
    "Salicylic Acid",
    "Phytic Acid",
    "Butyrospermum Parkii (Shea) Butter",
    "Fucus Vesiculosus Extract",
    "Curcuma Longa (Turmeric) Root Extract",
    "Aloe Barbadensis Flower Extract",
    "Allium Sativum (Garlic) Bulb Extract",
    "Laminaria Ochroleuca Extract",
    "Passiflora Incarnata Extract",
    "Salvia Officinalis (Sage) Leaf Extract",
    "Camphor",
    "Menthol",
    "Eucalyptus Globulus Leaf Extract",
    "Hamamelis Virginiana (Witch Hazel) Leaf Extract",
    "Solanum Melongena (Eggplant) Fruit Extract",
    "Cocamidopropyl Dimethylamine",
    "Sodium Methyl Oleoyl Taurate",
    "Dipotassium Glycyrrhizate",
    "Tetrasodium Glutamate Diacetate",
    "Polysorbate 80",
    "Melaleuca Alternifolia (Tea Tree) Leaf Oil",
    "Melia Azadirachta Leaf Extract",
    "Melia Azadirachta Flower Extract",
    "Corallina Officinalis Extract",
    "Melissa Officinalis Flower/Leaf/Stem Extract",
    "Coccinia Indica Fruit Extract",
    "Angelica Archangelica Extract",
    "Chamomilla Recutita (Matricaria) Flower Extract",
    "Citrus Limon (Lemon) Fruit Extract",
    "Echinacea Angustifolia Leaf Extract",
    "Ethylhexylglycerin",
    "Ocimum Basilicum (Basil) Flower/Leaf Extract",
    "Ocimum Sanctum Leaf Extract",
    "Anthemis Nobilis Flower Extract",
    "Ascorbic Acid",
    "Camellia Sinensis Leaf Extract",
    "Maltodextrin",
    "Silica",
    "Palmitic Acid",
    "Zinc PCA",
    "Kaolin",
    "Palmitoyl Tripeptide-5",
    "Aminomethyl Propanol",
    "Sodium Chloride",
    "Sodium Hydroxide",
    "Benzyl PCA",
    "Phenoxyethanol"
  ],
  "extended_contents": {},
  "tags": {
    "category": [
      "men",
      "mens"
    ],
    "product_type": [
      "serum",
      "mask",
      "treatment"
    ],
    "skin_type": [
      "oily",
      "sensitive",
      "acne-prone"
    ],
    "finish": [
      "matte",
      "sheer",
      "creamy",
      "gel",
      "oil",
      "foam"
    ],
    "color": [
      "clear"
    ],
    "ingredients": [
      "salicylic-acid",
      "peptides"
    ],
    "brand": [
      "mid-range",
      "mid-range"
    ],
    "special_features": [
      "cruelty-free",
      "vegan",
      "natural",
      "soothing"
    ]
  },
  "reviews": {
    "product_id": "pimprodacne-clearing-skin-wash-VP12691",
    "total_reviews": 0,
    "reviews": [],
    "paging": {
      "total_results": 0,
      "pages_total": 0,
      "page_size": 20,
      "current_page_number": 1
    },
    "rollup": {}
  }
}