{
  "product_id": "pimprod2053464",
  "product_url": "https://www.ulta.com/p/frizz-free-faves-holiday-kit-pimprod2053464",
  "extracted_at": "2025-09-23T03:56:48.016594+00:00",
  "product_name": "IGKFrizz-Free Faves Holiday Kit",
  "brand": "IGK",
  "categories": [
    "Home",
    "Gifts",
    "By Category",
    "Hair Gifts"
  ],
  "category_keys": [
    "home",
    "gifts",
    "by-category",
    "hair"
  ],
  "currency": "USD",
  "list_price": "",
  "sale_price": "49.00",
  "availability": "in_stock",
  "rating_avg": "",
  "rating_count": "",
  "images": [
    "https://media.ulta.com/i/ulta/2644153?w=500&h=500"
  ],
  "detailed_images": [
    "https://media.ulta.com/i/ulta/2644153?w=600&h=600&fmt=auto",
    "https://media.ulta.com/i/ulta/2644153_alt01?w=600&h=600&fmt=auto",
    "https://media.ulta.com/i/ulta/2644153_alt02?w=600&h=600&fmt=auto",
    "https://media.ulta.com/i/ulta/2644153_alt03?w=600&h=600&fmt=auto",
    "https://media.ulta.com/i/ulta/2644153_alt04?w=600&h=600&fmt=auto",
    "https://media.ulta.com/i/ulta/2644153_alt05?w=600&h=600&fmt=auto",
    "https://media.ulta.com/i/ulta/2644153_alt06?w=600&h=600&fmt=auto",
    "https://media.ulta.com/i/ulta/2644153_alt07?w=600&h=600&fmt=auto",
    "https://media.ulta.com/v/ulta/2644153_vid01/thumbs/fc2be3e7-9a7f-4510-8d6a-48ab6da60ec7?w=600&h=337&fmt=auto"
  ],
  "summary": "SummaryHighlightsCruelty FreeVeganSustainable PackagingIGK's best-selling smoothing routine is the ultimate solution for frizz-free, silky, keratin-like hair that lasts for up to 4 days. Prime, protect, and perfect for your smoothest hair ever.",
  "details": "DetailsBenefitsProvides up to 4 days of frizz controlProvides 450F degree heat protectionSmooth, Keratin-like resultsKey IngredientsSpirulina Protein: Strengthens and nourishes hairCoconut Oil: Enhances shine and delivers an easy slip for detangling without breakageInnovative Bonding Polymers: Mimic the frizz-free, high-shine coating of a keratin treatment when activated by heatFormulated WithoutGlutenParabensSulfatesMineral OilSiliconePEGsItem 2644153How To UseGood Behavior 4-in-1 Prep Spray: Apply evenly to damp, clean hair before your styler and comb through.Good Behavior Spirulina Protein Smoothing Spray: Mist over damp hair in sections and comb through, ensuring every strand is thoroughly coated from root to tip.Good Behavior Flexible Hairspray: Mist over dry hair during and after styling and build for more hold and frizz control.Pre-caution: FLAMMABLE. CONTENTS UNDER PRESSURE.Avoid spraying near eyes. Protect from sunlight. Do not expose to temperatures exceeding 120째F (50째C). Do not pierce or burn, even after use. Keep away from heat/sparks/open flames/hot surfaces - no smoking. Do not spray on an open flame or other ignition source. Use only as directed. Intentional misuse by deliberately concentrating and inhaling contents may be harmful or fatal. Keep out of reach of children.IngredientsGood Behavior 4-in-1 Prep Spray: Aqua/Water/Eau, Cetearyl Alcohol, Silicone Quaternium-8, Spirulina Maxima Extract, Cocos Nucifera (Coconut) Oil, Glycerin, Panthenol, Rosa Canina Seed Oil, Salvia Hispanica Seed Oil, Helianthus Annuus (Sunflower) Seed Extract, Rosa Centifolia Flower Water, Sambucus Nigra Flower Water, Glycolic Acid, Behentrimonium Methosulfate, PEG-12 Dimethicone, Trideceth-10, Potassium Sorbate, Polyquaternium-59, Cetrimonium Chloride, Butylene Glycol, Sodium PCA, Sodium Lactate, Arginine, Aspartic Acid, Cystine Bis-PG-Propyl Silanetriol, PCA, Glycine, Alanine, Serine, Valine, Isoleucine, Proline, Threonine, Citric Acid, Histidine, Phenylalanine, Sodium Benzoate, Fragrance (Parfum), Phenoxyethanol, EthylhexylglycerinGood Behavior Spirulina Protien Smoothing Spray: Alcohol Denat., Hydrofluorocarbon 152a, Butyl Ester of PVM/MA Copolymer, PEG/PPG-17/18 Dimethicone, Aqua/Water/Eau, Parfum/Fragrance, Vanillin, C12-15 Alkyl Benzoate, Aminomethyl Propanol, Hydrolyzed Corn Protein, Hydrolyzed Soy Protein, Hydrolyzed Wheat Protein, Silicone Quaternium-16, Undeceth-11, PEG/PPG-18/18 Dimethicone, Glycerin, Cinnamidopropyltrimonium Chloride, Butyloctanol, Undeceth-5, Butylene Glycol, Spirulina Maxima Extract, Arctium Lappa Root ExtractGood Behavior Flexible Anti Frizz Hairspray: Hydrofluorocarbon 152a, Alcohol Denat., Disiloxane, C12-15 Alkyl Benzoate, Diphenylsiloxy Phenyl Trimethicone, Octylacrylamide/Acrylates/Butylaminoethyl Methacrylate Copolymer, Isodecyl Neopentanoate, Isododecane, Polyglyceryl-10 Pentaoleate, Spirulina Platensis Extract, Citrullus Lanatus (Watermelon) Fruit Extract, Persea Gratissima (Avocado) Oil, Water (Aqua/Eau), Aminomethyl Propanol, Polyquaternium-59, Butylene Glycol, Phenoxyethanol, Fragrance (Parfum), LimoneneShipping & Coupon RestrictionsShipping Restrictions : This item cannot be shipped via air.This brand is excluded from most Ulta Beauty coupons.See brand eligibility details",
  "how_to_use": "Good Behavior 4-in-1 Prep Spray: Apply evenly to damp, clean hair before your styler and comb through.Good Behavior Spirulina Protein Smoothing Spray: Mist over damp hair in sections and comb through, ensuring every strand is thoroughly coated from root to tip.Good Behavior Flexible Hairspray: Mist over dry hair during and after styling and build for more hold and frizz control.Pre-caution: FLAMMABLE. CONTENTS UNDER PRESSURE.Avoid spraying near eyes. Protect from sunlight. Do not expose to temperatures exceeding 120째F (50째C). Do not pierce or burn, even after use. Keep away from heat/sparks/open flames/hot surfaces - no smoking. Do not spray on an open flame or other ignition source. Use only as directed. Intentional misuse by deliberately concentrating and inhaling contents may be harmful or fatal. Keep out of reach of children.",
  "ingredients": [
    "Good Behavior 4-in-1 Prep Spray: Aqua/Water/Eau",
    "Cetearyl Alcohol",
    "Silicone Quaternium-8",
    "Spirulina Maxima Extract",
    "Cocos Nucifera (Coconut) Oil",
    "Glycerin",
    "Panthenol",
    "Rosa Canina Seed Oil",
    "Salvia Hispanica Seed Oil",
    "Helianthus Annuus (Sunflower) Seed Extract",
    "Rosa Centifolia Flower Water",
    "Sambucus Nigra Flower Water",
    "Glycolic Acid",
    "Behentrimonium Methosulfate",
    "PEG-12 Dimethicone",
    "Trideceth-10",
    "Potassium Sorbate",
    "Polyquaternium-59",
    "Cetrimonium Chloride",
    "Butylene Glycol",
    "Sodium PCA",
    "Sodium Lactate",
    "Arginine",
    "Aspartic Acid",
    "Cystine Bis-PG-Propyl Silanetriol",
    "PCA",
    "Glycine",
    "Alanine",
    "Serine",
    "Valine",
    "Isoleucine",
    "Proline",
    "Threonine",
    "Citric Acid",
    "Histidine",
    "Phenylalanine",
    "Sodium Benzoate",
    "Fragrance (Parfum)",
    "Phenoxyethanol",
    "EthylhexylglycerinGood Behavior Spirulina Protien Smoothing Spray: Alcohol Denat",
    "Hydrofluorocarbon 152a",
    "Butyl Ester of PVM/MA Copolymer",
    "PEG/PPG-17/18 Dimethicone",
    "Aqua/Water/Eau",
    "Parfum/Fragrance",
    "Vanillin",
    "C12-15 Alkyl Benzoate",
    "Aminomethyl Propanol",
    "Hydrolyzed Corn Protein",
    "Hydrolyzed Soy Protein",
    "Hydrolyzed Wheat Protein",
    "Silicone Quaternium-16",
    "Undeceth-11",
    "PEG/PPG-18/18 Dimethicone",
    "Glycerin",
    "Cinnamidopropyltrimonium Chloride",
    "Butyloctanol",
    "Undeceth-5",
    "Butylene Glycol",
    "Spirulina Maxima Extract",
    "Arctium Lappa Root ExtractGood Behavior Flexible Anti Frizz Hairspray: Hydrofluorocarbon 152a",
    "Alcohol Denat",
    "Disiloxane",
    "C12-15 Alkyl Benzoate",
    "Diphenylsiloxy Phenyl Trimethicone",
    "Octylacrylamide/Acrylates/Butylaminoethyl Methacrylate Copolymer",
    "Isodecyl Neopentanoate",
    "Isododecane",
    "Polyglyceryl-10 Pentaoleate",
    "Spirulina Platensis Extract",
    "Citrullus Lanatus (Watermelon) Fruit Extract",
    "Persea Gratissima (Avocado) Oil",
    "Water (Aqua/Eau)",
    "Aminomethyl Propanol",
    "Polyquaternium-59",
    "Butylene Glycol",
    "Phenoxyethanol",
    "Fragrance (Parfum)",
    "Limonene"
  ],
  "extended_contents": {},
  "tags": {
    "category": [
      "hair",
      "haircare"
    ],
    "product_type": [
      "day cream"
    ],
    "skin_type": [
      "dry"
    ],
    "finish": [
      "glossy",
      "sheer",
      "creamy",
      "oil"
    ],
    "ingredients": [
      "glycolic-acid",
      "fragrance",
      "sulfate-free"
    ],
    "brand": [
      "mid-range",
      "mid-range"
    ],
    "special_features": [
      "cruelty-free",
      "vegan"
    ]
  },
  "reviews": {
    "product_id": "pimprod2053464",
    "total_reviews": 0,
    "reviews": [],
    "paging": {
      "total_results": 0,
      "pages_total": 0,
      "page_size": 20,
      "current_page_number": 1
    },
    "rollup": {}
  }
}