{
  "product_id": "pimprod2053337",
  "product_url": "https://www.ulta.com/p/pore-fect-skin-edit-pimprod2053337",
  "extracted_at": "2025-09-23T04:51:59.280973+00:00",
  "product_name": "Kate SomervillePore-fect Skin Edit",
  "brand": "Kate Somerville",
  "categories": [
    "Home",
    "Skin Care",
    "Cleansers",
    "Cleansing Exfoliators"
  ],
  "category_keys": [
    "home",
    "skin-care",
    "cleansers",
    "cleansing-exfoliators"
  ],
  "currency": "USD",
  "list_price": "",
  "sale_price": "39.00",
  "availability": "in_stock",
  "rating_avg": "",
  "rating_count": "",
  "images": [
    "https://media.ulta.com/i/ulta/2643952?w=500&h=500"
  ],
  "detailed_images": [
    "https://media.ulta.com/i/ulta/2643952?w=600&h=600&fmt=auto",
    "https://media.ulta.com/i/ulta/2643952_alt01?w=600&h=600&fmt=auto",
    "https://media.ulta.com/i/ulta/2643952_alt02?w=600&h=600&fmt=auto",
    "https://media.ulta.com/i/ulta/2643952_alt03?w=600&h=600&fmt=auto",
    "https://media.ulta.com/i/ulta/2643952_alt04?w=600&h=600&fmt=auto",
    "https://media.ulta.com/i/ulta/2643952_alt05?w=600&h=600&fmt=auto",
    "https://media.ulta.com/i/ulta/2643952_alt06?w=600&h=600&fmt=auto",
    "https://media.ulta.com/i/ulta/2643952_alt07?w=600&h=600&fmt=auto"
  ],
  "summary": "SummaryKate Somerville's Pore-fect Skin Edit is a 3-Piece Cleanser Travel Kit. Available for a limited time at a 25% savings—treat yourself or gift it now!",
  "details": "DetailsBenefitsFrom glow boosters to blemish busters, this limited-edition trio has a travel-size cleanser for every skin type or concern—cheers to a radiant holiday season!Exfoliate with ExfoliKatePurify with EradiKateNourish with Goat MilkKey IngredientsGlycolic Acid + Lactic Acid in ExfoliKate Daily Cleanser: Refine the appearance of pores + help clear buildup on skin’s surface.Papaya, Pineapple + Pumpkin Enzymes in ExfoliKate Daily Cleanser: Naturally enhance skin exfoliation without overdrying.3% Sulfur in EradiKate Foaming Cleanser: This anti-microbial + anti-inflammatory acne-fighter helps eliminate excess oil, blemishes and sebaceous filaments while calming skin.Natural Oat Extract in EradiKate Foaming Cleanser: Helps to reduce, absorb + balance sebum.Goat Milk in Goat Milk Moisturizing Cleanser: Soothes dry, sensitive skin with natural milk proteins.Manuka Honey in Goat Milk Moisturizing Cleanser: Nourishes skin without any tightness, dryness or irritation.Jojoba + Avocado Oils in in Goat Milk Moisturizing Cleanser: Moisturize + condition.IncludesExfoliKate Cleanser Daily Foaming Wash (1.0 oz)EradiKate 3% Sulfur Daily Foaming Cleanser (1.0 oz)Goat Milk Moisturizing Cleanser (1.0 oz)Item 2643952How To UseExfoliKate Cleanser Daily Foaming Wash: Good for: Morning + Evening.How often: DailyApplication: Apply a small amount to wet face + neck, and massage gently for 30 seconds. Rinse and gently pat dry.EradiKate 3% Sulfur Daily Foaming Cleanser: Good for: Morning + Evening.How often: DailyApplication: Apply a small amount to wet face + massage gently for 30 seconds. Rinse with cool water, pat dry and continue with your normal skincare routine.Goat Milk Moisturizing Cleanser: Good for: Morning + Evening.How often: DailyApplication: Apply a small amount to damp face + neck, and massage gently for 30 seconds. Rinse and gently pat dry.IngredientsExfoliKate Cleanser Daily Foaming Wash: Aqua/Water/Eau, Stearic Acid, Sodium Cocoyl Glycinate, Lauramidopropyl Betaine, Glycerin, Hydroxypropyl Starch Phosphate, Cetearyl Phosphate, Xylitylglucoside, Dimethicone PEG-8 Meadowfoamate, Anhydroxylitol, Xylitol, Leuconostoc/Radish Root Ferment Filtrate, Bromelain, Papain, Lactobacillus/Pumpkin Fruit Ferment Filtrate, Lauramide DIPA, Aloe Barbadensis Leaf Juice Powder, Lactic Acid, Glycolic Acid, Citrus Aurantium Bergamia (Bergamot) Fruit Oil, Aniba Rosaeodora (Rosewood) Wood Extract, Citrus Aurantium Dulcis (Orange) Peel Oil, Glucose, Pelargonium Graveolens Flower Oil, Citral, Benzyl Benzoate, Benzyl Alcohol, Sodium Hydroxide, Limonene, Chlorphenesin, Linalool, Citronellol, Maltodextrin, Geraniol, CI 75810 (Chlorophyllin-Copper Complex).EradiKate 3% Sulfur Daily Foaming Cleanser: Active: Sulfur 3.0%.Inactive: Water/Aqua/Eau, Sodium Cocoyl Isethionate, Coco-Glucoside, Acrylates Copolymer, Cetearyl Alcohol, Glycereth-18 Ethylhexanoate, Glycereth-18, Stearyl Alcohol, Honey Extract/Mel/Extrait de Miel, Oryza Sativa (Rice) Bran Extract, Avena Sativa (Oat) Kernel Extract, Oligopeptide-10, Boswellia Serrata Extract, Behenyl Alcohol, Glycerin, Xanthan Gum, Caprylyl Glycol, Hexylene Glycol, Butylene Glycol, Phenoxyethanol, Fragrance/Parfum, Citric Acid, Sodium Hydroxide, Ethylhexylglycerin, Disodium EDTA, Disodium Carboxyethyl Siliconate, Linalool, Potassium Sorbate, Sodium Benzoate, Titanium Dioxide (CI 77891), Iron Oxides (CI 77491).Goat Milk Moisturizing Cleanser: Aqua/Water/Eau, Sodium Cocoyl Isethionate, Cocamidopropyl Hydroxysultaine, Glycerin, Betaine, Propanediol, Caprylic/Capric Triglyceride, Vitis Vinifera (Grape) Seed Oil, Simmondsia Chinensis (Jojoba) Seed Oil, Persea Gratissima (Avocado) Oil, Cocos Nucifera (Coconut) Oil, Xylitylglucoside, Polyglyceryl-3 Methylglucose Distearate, Polyacrylate Crosspolymer-6, Coconut Acid, 1,2-Hexanediol, Cetyl Palmitate, Glyceryl Stearate, Glyceryl Distearate, Cetearyl Alcohol, Caprae Lac/Goat Milk/Lait de Chèvre, Tocopherol, Mel Extract/Honey Extract/Extrait de Miel, Rosmarinus Officinalis (Rosemary) Leaf Extract, Helianthus Annuus (Sunflower) Extract, Bisabolol, Aloe Barbadensis Leaf Juice, Sodium Lauroyl Glutamate, Oryza Sativa (Rice) Bran Extract, Xylitol, Anhydroxylitol, Parfum/Fragrance, Stearic Acid, Disodium EDTA, Sodium Hydroxide, Xanthan Gum, t-butyl Alcohol, Ethylhexylglycerin, Phenoxyethanol, Benzyl Salicylate.Shipping & Coupon RestrictionsThis brand is excluded from most Ulta Beauty coupons.See brand eligibility details",
  "how_to_use": "ExfoliKate Cleanser Daily Foaming Wash: Good for: Morning + Evening.How often: DailyApplication: Apply a small amount to wet face + neck, and massage gently for 30 seconds. Rinse and gently pat dry.EradiKate 3% Sulfur Daily Foaming Cleanser: Good for: Morning + Evening.How often: DailyApplication: Apply a small amount to wet face + massage gently for 30 seconds. Rinse with cool water, pat dry and continue with your normal skincare routine.Goat Milk Moisturizing Cleanser: Good for: Morning + Evening.How often: DailyApplication: Apply a small amount to damp face + neck, and massage gently for 30 seconds. Rinse and gently pat dry.",
  "ingredients": [
    "ExfoliKate Cleanser Daily Foaming Wash: Aqua/Water/Eau",
    "Stearic Acid",
    "Sodium Cocoyl Glycinate",
    "Lauramidopropyl Betaine",
    "Glycerin",
    "Hydroxypropyl Starch Phosphate",
    "Cetearyl Phosphate",
    "Xylitylglucoside",
    "Dimethicone PEG-8 Meadowfoamate",
    "Anhydroxylitol",
    "Xylitol",
    "Leuconostoc/Radish Root Ferment Filtrate",
    "Bromelain",
    "Papain",
    "Lactobacillus/Pumpkin Fruit Ferment Filtrate",
    "Lauramide DIPA",
    "Aloe Barbadensis Leaf Juice Powder",
    "Lactic Acid",
    "Glycolic Acid",
    "Citrus Aurantium Bergamia (Bergamot) Fruit Oil",
    "Aniba Rosaeodora (Rosewood) Wood Extract",
    "Citrus Aurantium Dulcis (Orange) Peel Oil",
    "Glucose",
    "Pelargonium Graveolens Flower Oil",
    "Citral",
    "Benzyl Benzoate",
    "Benzyl Alcohol",
    "Sodium Hydroxide",
    "Limonene",
    "Chlorphenesin",
    "Linalool",
    "Citronellol",
    "Maltodextrin",
    "Geraniol",
    "Sodium Cocoyl Isethionate",
    "Coco-Glucoside",
    "Acrylates Copolymer",
    "Cetearyl Alcohol",
    "Glycereth-18 Ethylhexanoate",
    "Glycereth-18",
    "Stearyl Alcohol",
    "Honey Extract/Mel/Extrait de Miel",
    "Oryza Sativa (Rice) Bran Extract",
    "Avena Sativa (Oat) Kernel Extract",
    "Oligopeptide-10",
    "Boswellia Serrata Extract",
    "Behenyl Alcohol",
    "Glycerin",
    "Xanthan Gum",
    "Caprylyl Glycol",
    "Hexylene Glycol",
    "Butylene Glycol",
    "Phenoxyethanol",
    "Fragrance/Parfum",
    "Citric Acid",
    "Sodium Hydroxide",
    "Ethylhexylglycerin",
    "Disodium EDTA",
    "Disodium Carboxyethyl Siliconate",
    "Linalool",
    "Potassium Sorbate",
    "Sodium Benzoate",
    "Titanium Dioxide (",
    "Iron Oxides (",
    "Sodium Cocoyl Isethionate",
    "Cocamidopropyl Hydroxysultaine",
    "Glycerin",
    "Betaine",
    "Propanediol",
    "Caprylic/Capric Triglyceride",
    "Vitis Vinifera (Grape) Seed Oil",
    "Simmondsia Chinensis (Jojoba) Seed Oil",
    "Persea Gratissima (Avocado) Oil",
    "Cocos Nucifera (Coconut) Oil",
    "Xylitylglucoside",
    "Polyglyceryl-3 Methylglucose Distearate",
    "Polyacrylate Crosspolymer-6",
    "Coconut Acid",
    "2-Hexanediol",
    "Cetyl Palmitate",
    "Glyceryl Stearate",
    "Glyceryl Distearate",
    "Cetearyl Alcohol",
    "Caprae Lac/Goat Milk/Lait de Chèvre",
    "Tocopherol",
    "Mel Extract/Honey Extract/Extrait de Miel",
    "Rosmarinus Officinalis (Rosemary) Leaf Extract",
    "Helianthus Annuus (Sunflower) Extract",
    "Bisabolol",
    "Aloe Barbadensis Leaf Juice",
    "Sodium Lauroyl Glutamate",
    "Oryza Sativa (Rice) Bran Extract",
    "Xylitol",
    "Anhydroxylitol",
    "Parfum/Fragrance",
    "Stearic Acid",
    "Disodium EDTA",
    "Sodium Hydroxide",
    "Xanthan Gum",
    "t-butyl Alcohol",
    "Ethylhexylglycerin",
    "Phenoxyethanol",
    "Benzyl Salicylate"
  ],
  "extended_contents": {},
  "tags": {
    "product_type": [
      "cleanser"
    ],
    "skin_type": [
      "dry",
      "sensitive",
      "acne-prone",
      "normal"
    ],
    "finish": [
      "dewy",
      "powdery",
      "oil",
      "foam"
    ],
    "ingredients": [
      "glycolic-acid",
      "lactic-acid",
      "peptides",
      "fragrance"
    ],
    "brand": [
      "mid-range",
      "mid-range"
    ],
    "special_features": [
      "natural",
      "hydrating",
      "brightening",
      "soothing"
    ],
    "category": []
  },
  "reviews": {
    "product_id": "pimprod2053337",
    "total_reviews": 0,
    "reviews": [],
    "paging": {
      "total_results": 0,
      "pages_total": 0,
      "page_size": 20,
      "current_page_number": 1
    },
    "rollup": {}
  }
}