{
  "product_id": "pimprod2053652",
  "product_url": "https://www.ulta.com/p/deep-vita-c-capsule-cream-pimprod2053652",
  "extracted_at": "2025-09-23T03:45:06.784165+00:00",
  "product_name": "medicubeDeep Vita C Capsule Cream",
  "brand": "medicube",
  "categories": [
    "Home",
    "Skin Care",
    "Moisturizers",
    "Face Moisturizer"
  ],
  "category_keys": [
    "home",
    "skin-care",
    "moisturizers",
    "face"
  ],
  "currency": "USD",
  "list_price": "",
  "sale_price": "22.00",
  "availability": "in_stock",
  "rating_avg": "5",
  "rating_count": "3",
  "images": [
    "https://media.ulta.com/i/ulta/2645371?w=500&h=500"
  ],
  "detailed_images": [
    "https://media.ulta.com/i/ulta/2645371?w=600&h=600&fmt=auto",
    "https://media.ulta.com/i/ulta/2645371_alt01?w=600&h=600&fmt=auto",
    "https://media.ulta.com/i/ulta/2645371_alt02?w=600&h=600&fmt=auto",
    "https://media.ulta.com/i/ulta/2645371_alt03?w=600&h=600&fmt=auto",
    "https://media.ulta.com/i/ulta/2645371_alt04?w=600&h=600&fmt=auto",
    "https://media.ulta.com/i/ulta/2645371_alt05?w=600&h=600&fmt=auto",
    "https://media.ulta.com/i/ulta/2645371_alt06?w=600&h=600&fmt=auto",
    "https://media.ulta.com/i/ulta/2645371_alt07?w=600&h=600&fmt=auto"
  ],
  "summary": "SummaryIntroducing Medicube Deep Vita C Capsule Cream, a revolutionary skincare solution designed to care for uneven skin tone and spots, leaving your skin bright, radiant, and even-toned with stablized liposome Vitamin C capsules.",
  "details": "DetailsBenefitsEncapsulated Vitamin C– Fades dark spots and boosts radiance with maximum freshness and effectiveness without oxidationCustomizable Mark-Blast Mix –Customize the capsule-to-gel ratio for a stable, soothing blend that absorbs effortlessly into the skin for everyday useProven Skin Radiance Improvement - Skin radiance improved by 34.8% immediately and by 32.6% after 24 hours, providing both instant and lasting resultsFeaturesDual-texture allowing you to tailor the formula to suit your skin's needs on finle lines and brighteningLightweight gel texture– Absorbs quickly and is gentle enough for sensitive skinDermatologist-tested, low-irritation test completedResearch ResultsArea of uneven skin tone visibility improved by 20.1%Uneven skin tone and spot visibility improved by 3.0%Under-eye darkness visibility improved by 1.0%Uneven skin tone in the cheek area improved by 1.4%Melanin visible area within the skin improved by 5.2%Melanin pigment visibility improved by 4.0%Skin tone improvement improved by 5.4%Surface moisturization improved by 13.4%Inner skin moisturization improved by 4.1%Skin barrier improved by 7.5%Skin roughness improved by 5.2%Skin radiance improved by 34.8% (Immediately)Skin radiance improved by 32.6% (After 24 hours)Deep pigmentation and blemishes of 10 years+ improved by 1.5%Visible melanin area within the skin improved by 4.4% (After 7 days)Area of uneven skin tone visibility improved by 12.9%Evenness of skin tone improved by 18.2%Excerpt from the Clinical Trial Report on Medicube Deep Vita C Capsule Cream. Individual results may vary.Item 2645371How To UseMix the vitamin capsule and transparent gel in a suitable ratio based on your skin type. For a lighter feel, increase the ratio of the gel, while for more hydration and elasticity, increase the ratio of the capsule.Apply the mixture morning and evening to face and neck, after serum.[Ration for skin type] -For oily skin: Transparent gel 2 + Vitamin C capsule 1For normal & combination skin: Transparent gel 1 + Vitamin C capsule 1For dry & sensitive skin:For oily skin: Transparent gel 1 + Vitamin C capsule 2For external use only. Discontinue use if irritation occurs. Keep out of reach of children. *Read instructions and caution before use.IngredientsHippophae Rhamnoides Water, Glycerin, Water, Niacinamide, Methylpropanediol, Propanediol, 1,2-Hexanediol, Butylene Glycol, Dipropylene Glycol, Caprylic/Capric Triglyceride, Glycereth-26, Ethylhexyl Palmitate, Cetearyl Alcohol, Arginine, Carbomer, Ammonium Acryloyldimethyltaurate/VP Copolymer, Cetearyl Olivate, Helianthus Annuus (Sunflower) Seed Oil, Sorbitan Olivate, Simethicone, Polyglyceryl-10 Laurate, Ethylhexylglycerin, Adenosine, Fragrance, Polyacrylate-13, Glycine Soja (Soybean) Oil, Disodium EDTA, Polyisobutene, Hydrolyzed Sclerotium Gum, Glyceryl Stearate, Gluconolactone, Polysorbate 20, Sorbitan Isostearate, Hydrogenated Lecithin, Bixa Orellana Seed Oil, Polyglyceryl-10 Stearate, Alpha-Arbutin, Panthenol, Sodium Ascorbyl Phosphate, Pentylene Glycol, Ferulic acid, Tocopherol, Ascorbyl Glucoside, 3-O-Ethyl Ascorbic Acid, Bisabolol, Ascorbic Acid, Hydroxyphenyl Propamidobenzoic Acid, Pyridoxine, Ubiquinone, Biotin, Folic Acid, Sodium Hyaluronate, Ascorbyl Propyl Hyaluronate, Ascorbyl Palmitate, Cyanocobalamin, Thiamine HCl, Riboflavin, Linoleic Acid, Beta-Carotene, Rutin, Hydroxycinnamic Acid.Shipping & Coupon RestrictionsThis brand is excluded from most Ulta Beauty coupons.See brand eligibility details",
  "how_to_use": "Mix the vitamin capsule and transparent gel in a suitable ratio based on your skin type. For a lighter feel, increase the ratio of the gel, while for more hydration and elasticity, increase the ratio of the capsule.Apply the mixture morning and evening to face and neck, after serum.[Ration for skin type] -For oily skin: Transparent gel 2 + Vitamin C capsule 1For normal & combination skin: Transparent gel 1 + Vitamin C capsule 1For dry & sensitive skin:For oily skin: Transparent gel 1 + Vitamin C capsule 2For external use only. Discontinue use if irritation occurs. Keep out of reach of children. *Read instructions and caution before use.",
  "ingredients": [
    "Hippophae Rhamnoides Water",
    "Glycerin",
    "Water",
    "Niacinamide",
    "Methylpropanediol",
    "Propanediol",
    "2-Hexanediol",
    "Butylene Glycol",
    "Dipropylene Glycol",
    "Caprylic/Capric Triglyceride",
    "Glycereth-26",
    "Ethylhexyl Palmitate",
    "Cetearyl Alcohol",
    "Arginine",
    "Carbomer",
    "Ammonium Acryloyldimethyltaurate/VP Copolymer",
    "Cetearyl Olivate",
    "Helianthus Annuus (Sunflower) Seed Oil",
    "Sorbitan Olivate",
    "Simethicone",
    "Polyglyceryl-10 Laurate",
    "Ethylhexylglycerin",
    "Adenosine",
    "Fragrance",
    "Polyacrylate-13",
    "Glycine Soja (Soybean) Oil",
    "Disodium EDTA",
    "Polyisobutene",
    "Hydrolyzed Sclerotium Gum",
    "Glyceryl Stearate",
    "Gluconolactone",
    "Polysorbate 20",
    "Sorbitan Isostearate",
    "Hydrogenated Lecithin",
    "Bixa Orellana Seed Oil",
    "Polyglyceryl-10 Stearate",
    "Alpha-Arbutin",
    "Panthenol",
    "Sodium Ascorbyl Phosphate",
    "Pentylene Glycol",
    "Ferulic acid",
    "Tocopherol",
    "Ascorbyl Glucoside",
    "3-O-Ethyl Ascorbic Acid",
    "Bisabolol",
    "Ascorbic Acid",
    "Hydroxyphenyl Propamidobenzoic Acid",
    "Pyridoxine",
    "Ubiquinone",
    "Biotin",
    "Folic Acid",
    "Sodium Hyaluronate",
    "Ascorbyl Propyl Hyaluronate",
    "Ascorbyl Palmitate",
    "Cyanocobalamin",
    "Thiamine HCl",
    "Riboflavin",
    "Linoleic Acid",
    "Beta-Carotene",
    "Rutin",
    "Hydroxycinnamic Acid"
  ],
  "extended_contents": {},
  "tags": {
    "category": [
      "face"
    ],
    "product_type": [
      "moisturizer"
    ],
    "skin_type": [
      "oily",
      "dry",
      "combination",
      "sensitive",
      "acne-prone",
      "normal"
    ],
    "finish": [
      "dewy",
      "sheer",
      "long-wear",
      "cream",
      "gel",
      "oil"
    ],
    "ingredients": [
      "niacinamide",
      "fragrance"
    ],
    "brand": [
      "mid-range",
      "affordable"
    ],
    "special_features": [
      "dermatologist-tested",
      "brightening",
      "soothing"
    ]
  },
  "reviews": {
    "product_id": "pimprod2053652",
    "total_reviews": 3,
    "reviews": [
      {
        "review_id": 563225017,
        "rating": 5,
        "headline": "Nice texture!",
        "comments": "This is so hydrating! I like the texture because it feels rich and keeps my skin feeling plump. I use it at the end of my skincare routine morning and night and I can see more of a glow overall.",
        "nickname": "SM",
        "location": "California",
        "created_date": 1757616710087,
        "bottom_line": "Yes",
        "helpful_votes": 3,
        "not_helpful_votes": 0
      },
      {
        "review_id": 560452906,
        "rating": 5,
        "headline": "I",
        "comments": "Perfect for my skin",
        "nickname": "Elaine",
        "location": "Harlingen",
        "created_date": 1755621084273,
        "bottom_line": "Yes",
        "helpful_votes": 3,
        "not_helpful_votes": 2
      },
      {
        "review_id": 559847532,
        "rating": 5,
        "headline": "THE ABSOLUTE BEST PURCHASE",
        "comments": "Get IT, RUN, this product to a tea is hands down the most hydrating thing for my combination skin type it dosent. It hydrates the dryness of my skin and helps the oily part of my skin as well, while making my acne scars dissapear. I do recommend this more for dry skin though!",
        "nickname": "Payton",
        "location": "Dallas",
        "created_date": 1754693069178,
        "bottom_line": null,
        "helpful_votes": 25,
        "not_helpful_votes": 1
      }
    ],
    "paging": {
      "total_results": 3,
      "pages_total": 1,
      "page_size": 20,
      "current_page_number": 1
    },
    "rollup": {
      "properties": [],
      "rating_histogram": [
        0,
        0,
        0,
        0,
        3
      ],
      "review_histogram": [
        0,
        0,
        0,
        0,
        3
      ],
      "rating_count": 3,
      "review_count": 3,
      "average_rating": 5.0,
      "recommended_ratio": 1.0,
      "media": [],
      "name": "Deep Vita C Capsule Cream",
      "native_review_count": 3,
      "native_sampling_review_count": 0,
      "native_sweepstakes_review_count": 0,
      "native_community_content_review_count": 0,
      "syndicated_review_count": 0,
      "locale": "en_US"
    }
  }
}