{
  "product_id": "pimprod2052512",
  "product_url": "https://www.ulta.com/p/collagen-hydrogel-eye-patch-pimprod2052512",
  "extracted_at": "2025-09-23T03:38:45.377278+00:00",
  "product_name": "MixsoonCollagen Hydrogel Eye Patch",
  "brand": "Mixsoon",
  "categories": [
    "Home",
    "Skin Care",
    "Eye Treatments",
    "Eye Masks"
  ],
  "category_keys": [
    "home",
    "skin-care",
    "eye-treatments",
    "masks"
  ],
  "currency": "USD",
  "list_price": "",
  "sale_price": "30.00",
  "availability": "in_stock",
  "rating_avg": "",
  "rating_count": "",
  "images": [
    "https://media.ulta.com/i/ulta/2643841?w=500&h=500"
  ],
  "detailed_images": [
    "https://media.ulta.com/i/ulta/2643841?w=600&h=600&fmt=auto",
    "https://media.ulta.com/i/ulta/2643841_alt01?w=600&h=600&fmt=auto",
    "https://media.ulta.com/i/ulta/2643841_alt02?w=600&h=600&fmt=auto",
    "https://media.ulta.com/i/ulta/2643841_alt03?w=600&h=600&fmt=auto",
    "https://media.ulta.com/i/ulta/2643841_alt04?w=600&h=600&fmt=auto"
  ],
  "summary": "SummaryHighlightsClean IngredientsGive BackThe Collagen Hydrogel Eye Patch from Mixsoon delivers deep hydration and a radiant glowâ€”perfect for those dealing with sagging skin, fine lines, or loss of elasticity around the eyes.",
  "details": "DetailsBenefitsIdeal for anyone who finds traditional eye creams too heavy and struggles with tired-looking eyesThese eye patches are effective on dark spots and blemishes when used on the cheeks and foreheadThe spatula included in the packaging helps with easier, more hygienic useKey IngredientsHydrolyzed Collagen - Improves the appearance of fine lines, boosts skin elasticity, and enhanced overall skin hydrationItem 2643841How To UseApply the eye patches on under eye area after cleansing and leave on for 20-30 minutes. Gently pat to aid absorption.IngredientsWater, Glycerin, Niacinamide, Carrageenan, Butylene Glycol, 1,2-Hexanediol, Potassium Chloride, Hydroxyacetophenone, Cyamopsis Tetragonoloba (Guar) Gum, Cellulose Gum, Ceratonia Siliqua (Carob) Gum, Allantoin, Propanediol, Polyglyceryl-10 Laurate, Panthenol, Sucrose, Calcium Chloride, Dipotassium Glycyrrhizate, Caprylyl Glycol, Adenosine, Ethylhexylglycerin, Arginine, Disodium EDTA, Hydrolyzed Collagen, Glycine, Glutamic Acid, Aspartic Acid, Acetyl Hexapeptide-8, Copper Tripeptide-1, Oligopeptide-29, Oligopeptide-32, Lysine, Histidine, Threonine, Serine, Proline, Alanine, Valine, Methionine, Isoleucine, Leucine, Tyrosine, Phenylalanine, Cysteine, Palmitoyl Pentapeptide-4.Shipping & Coupon RestrictionsThis brand is excluded from most Ulta Beauty coupons.See brand eligibility details",
  "how_to_use": "Apply the eye patches on under eye area after cleansing and leave on for 20-30 minutes. Gently pat to aid absorption.",
  "ingredients": [
    "Water",
    "Glycerin",
    "Niacinamide",
    "Carrageenan",
    "Butylene Glycol",
    "2-Hexanediol",
    "Potassium Chloride",
    "Hydroxyacetophenone",
    "Cyamopsis Tetragonoloba (Guar) Gum",
    "Cellulose Gum",
    "Ceratonia Siliqua (Carob) Gum",
    "Allantoin",
    "Propanediol",
    "Polyglyceryl-10 Laurate",
    "Panthenol",
    "Sucrose",
    "Calcium Chloride",
    "Dipotassium Glycyrrhizate",
    "Caprylyl Glycol",
    "Adenosine",
    "Ethylhexylglycerin",
    "Arginine",
    "Disodium EDTA",
    "Hydrolyzed Collagen",
    "Glycine",
    "Glutamic Acid",
    "Aspartic Acid",
    "Acetyl Hexapeptide-8",
    "Copper Tripeptide-1",
    "Oligopeptide-29",
    "Oligopeptide-32",
    "Lysine",
    "Histidine",
    "Threonine",
    "Serine",
    "Proline",
    "Alanine",
    "Valine",
    "Methionine",
    "Isoleucine",
    "Leucine",
    "Tyrosine",
    "Phenylalanine",
    "Cysteine",
    "Palmitoyl Pentapeptide-4"
  ],
  "extended_contents": {},
  "tags": {
    "category": [
      "eye",
      "eyes"
    ],
    "product_type": [
      "cleanser",
      "mask",
      "treatment",
      "eye cream"
    ],
    "skin_type": [
      "acne-prone"
    ],
    "finish": [
      "dewy",
      "sheer",
      "cream",
      "gel"
    ],
    "ingredients": [
      "niacinamide",
      "peptides",
      "collagen"
    ],
    "brand": [
      "mid-range",
      "mid-range"
    ],
    "special_features": [
      "brightening",
      "purifying"
    ]
  },
  "reviews": {
    "product_id": "pimprod2052512",
    "total_reviews": 0,
    "reviews": [],
    "paging": {
      "total_results": 0,
      "pages_total": 0,
      "page_size": 20,
      "current_page_number": 1
    },
    "rollup": {}
  }
}