{
  "product_id": "pimprod2052556",
  "product_url": "https://www.ulta.com/p/double-vita-capsule-cleansing-foam-pimprod2052556",
  "extracted_at": "2025-09-23T03:47:24.478877+00:00",
  "product_name": "NEOGENDouble Vita Capsule Cleansing Foam",
  "brand": "NEOGEN",
  "categories": [
    "Home",
    "Skin Care",
    "Cleansers",
    "Face Wash"
  ],
  "category_keys": [
    "home",
    "skin-care",
    "cleansers",
    "face"
  ],
  "currency": "USD",
  "list_price": "",
  "sale_price": "23.00",
  "availability": "in_stock",
  "rating_avg": "5",
  "rating_count": "1",
  "images": [
    "https://media.ulta.com/i/ulta/2645132?w=500&h=500"
  ],
  "detailed_images": [
    "https://media.ulta.com/i/ulta/2645132?w=600&h=600&fmt=auto",
    "https://media.ulta.com/i/ulta/2645132_alt01?w=600&h=600&fmt=auto",
    "https://media.ulta.com/i/ulta/2645132_alt02?w=600&h=600&fmt=auto",
    "https://media.ulta.com/i/ulta/2645132_alt03?w=600&h=600&fmt=auto",
    "https://media.ulta.com/i/ulta/2645132_alt04?w=600&h=600&fmt=auto",
    "https://media.ulta.com/i/ulta/2645132_alt05?w=600&h=600&fmt=auto",
    "https://media.ulta.com/i/ulta/2645132_alt06?w=600&h=600&fmt=auto",
    "https://media.ulta.com/i/ulta/2645132_alt07?w=600&h=600&fmt=auto"
  ],
  "summary": "SummaryHighlightsClean IngredientsThe Double Vita Capsule Cleansing Foam from Neogen is formulated with Double Vita capsule beads and a gel formula that provides smooth and radiant skin texture.",
  "details": "DetailsBenefitsLightweight, mildly acidic gel cleanser with a gentle formula that effectively cleanses while leaving skin feeling fresh and balancedGentle gel cleansing foam that brightens dull skin and delivers deep hydration for a soft, radiant complexionKey IngredientsAHA - Reduces the appearance of fine lines and wrinklesBHA - Controls excess sebum and combats uneven skin tonePapaya Enzyme - Gently removes dead skin cells, unclog pores, and helps reduce inflammationItem 2645132How To UseLather up an appropriate with damp hands and massage on face. Rinse off with lukewarm water.IngredientsWater, Lauryl Hydroxysultaine, Potassium Cocoyl Glycinate, Sodium Chloride, Acrylates Copolymer, Disodium Cocoamphodiacetate, Potassium Cocoate, C12-14 Alketh-12, Fragrance, Mannitol, Potassium Benzoate, Microcrystalline Cellulose, Limonene, Hexylene Glycol, Zea Mays (Corn) Starch, Ethylhexylglycerin, Benzyl Benzoate, Glycerin, Linalool, Mica, Hexyl Cinnamal, Butylene Glycol, Synthetic Fluorphlogopite, Citric Acid, Niacinamide, 1,2-Hexanediol, Hydrogenated Lecithin, Adenosine, Citral, Polyglyceryl-10 Laurate, CI 77492 (Iron Oxides, Yellow), CI 77491 (Iron Oxides, Red), Citrus Aurantifolia (Lime) Fruit Extract, Salicylic Acid, Citrus Junos Fruit Extract, Calcium Pantothenate, Maltodextrin, Sodium Starch Octenylsuccinate, Papain, Citronellol, Sodium Ascorbyl Phosphate, Glucose, Tocopheryl Acetate, Pyridoxine HCl, Xanthan Gum, Ascorbyl Tetraisopalmitate, Panthenol, Caprylyl Glycol, Glutathione, Geraniol, Arbutin, Tranexamic Acid, Sodium Hyaluronate, Chondrus Crispus Extract, Ascorbic Acid, Biotin, Pyridoxine, Folic Acid, Hydroxypropyltrimonium Hyaluronate, Cyanocobalamin, Tocopherol, Hydrolyzed Hyaluronic Acid, Sodium Acetylated Hyaluronate, Riboflavin, Thiamine HCl, Linoleic Acid, Beta-Carotene, Hyaluronic Acid, Sodium Hyaluronate Crosspolymer, Hydrolyzed Sodium Hyaluronate, Potassium Hyaluronate.Shipping & Coupon RestrictionsThis brand is excluded from most Ulta Beauty coupons.See brand eligibility details",
  "how_to_use": "Lather up an appropriate with damp hands and massage on face. Rinse off with lukewarm water.",
  "ingredients": [
    "Water",
    "Lauryl Hydroxysultaine",
    "Potassium Cocoyl Glycinate",
    "Sodium Chloride",
    "Acrylates Copolymer",
    "Disodium Cocoamphodiacetate",
    "Potassium Cocoate",
    "C12-14 Alketh-12",
    "Fragrance",
    "Mannitol",
    "Potassium Benzoate",
    "Microcrystalline Cellulose",
    "Limonene",
    "Hexylene Glycol",
    "Zea Mays (Corn) Starch",
    "Ethylhexylglycerin",
    "Benzyl Benzoate",
    "Glycerin",
    "Linalool",
    "Mica",
    "Hexyl Cinnamal",
    "Butylene Glycol",
    "Synthetic Fluorphlogopite",
    "Citric Acid",
    "Niacinamide",
    "2-Hexanediol",
    "Hydrogenated Lecithin",
    "Adenosine",
    "Citral",
    "Polyglyceryl-10 Laurate",
    "Yellow)",
    "Red)",
    "Citrus Aurantifolia (Lime) Fruit Extract",
    "Salicylic Acid",
    "Citrus Junos Fruit Extract",
    "Calcium Pantothenate",
    "Maltodextrin",
    "Sodium Starch Octenylsuccinate",
    "Papain",
    "Citronellol",
    "Sodium Ascorbyl Phosphate",
    "Glucose",
    "Tocopheryl Acetate",
    "Pyridoxine HCl",
    "Xanthan Gum",
    "Ascorbyl Tetraisopalmitate",
    "Panthenol",
    "Caprylyl Glycol",
    "Glutathione",
    "Geraniol",
    "Arbutin",
    "Tranexamic Acid",
    "Sodium Hyaluronate",
    "Chondrus Crispus Extract",
    "Ascorbic Acid",
    "Biotin",
    "Pyridoxine",
    "Folic Acid",
    "Hydroxypropyltrimonium Hyaluronate",
    "Cyanocobalamin",
    "Tocopherol",
    "Hydrolyzed Hyaluronic Acid",
    "Sodium Acetylated Hyaluronate",
    "Riboflavin",
    "Thiamine HCl",
    "Linoleic Acid",
    "Beta-Carotene",
    "Hyaluronic Acid",
    "Sodium Hyaluronate Crosspolymer",
    "Hydrolyzed Sodium Hyaluronate",
    "Potassium Hyaluronate"
  ],
  "extended_contents": {
    "text": "Show less"
  },
  "tags": {
    "category": [
      "face"
    ],
    "product_type": [
      "cleanser"
    ],
    "skin_type": [
      "sensitive",
      "mature",
      "normal"
    ],
    "finish": [
      "matte",
      "dewy",
      "sheer",
      "creamy",
      "gel",
      "foam"
    ],
    "ingredients": [
      "hyaluronic-acid",
      "niacinamide",
      "salicylic-acid",
      "synthetic",
      "fragrance"
    ],
    "brand": [
      "mid-range",
      "affordable"
    ],
    "special_features": [
      "anti-aging",
      "brightening",
      "soothing",
      "purifying"
    ]
  },
  "reviews": {
    "product_id": "pimprod2052556",
    "total_reviews": 1,
    "reviews": [],
    "paging": {
      "total_results": 0,
      "pages_total": 0,
      "page_size": 20,
      "current_page_number": 1
    },
    "rollup": {
      "properties": [],
      "rating_histogram": [
        0,
        0,
        0,
        0,
        1
      ],
      "review_histogram": [
        0,
        0,
        0,
        0,
        1
      ],
      "rating_count": 1,
      "review_count": 1,
      "average_rating": 5.0,
      "recommended_ratio": 1.0,
      "media": [],
      "native_review_count": 0,
      "native_sampling_review_count": 0,
      "native_sweepstakes_review_count": 0,
      "native_community_content_review_count": 0,
      "syndicated_review_count": 1,
      "locale": "en_US"
    }
  }
}